Workbook
Name DatosExternos_1: BD!$A$1:$E$3588
Name DES.1: 'LISTA SABANA'!$G$12
Name DES.1: 'LISTA SABANA'!$G$12
Name DES.2: 'LISTA SABANA'!$I$12
Name DES.2: 'LISTA SABANA'!$I$12

Sheet ÍNDICE
A1: INDICE | H1: Seleccione el Producto a consultar | AV1: =IFERROR(VLOOKUP("*"&$H$3&"*",$A$2:$A$23,1,0),VLOOKUP("*"&$H$3&"*",$B$2:$B$26,1,0)) -> CONECTORES NEUMÁTICOS
A2: {=+HYPERLINK("#"&CELL("direccion",INDIRECT("'LISTA SABANA'!B"&C2)),INDEX('LISTA SABANA'!C:C,C2,1))} -> PLASTICOS | B2: {=+HYPERLINK("#"&CELL("direccion",INDIRECT("'LISTA SABANA'!B"&E2)),INDEX('LISTA SABANA'!C:C,E2,1))} -> ARANDELAS DE COBRE | C2: =+MATCH(D2,'LISTA SABANA'!C:C,0) -> 14 | D2: PLASTICOS | E2: =+MATCH(F2,'LISTA SABANA'!C:C,0) -> 1979 | F2: ARANDELAS DE COBRE | H2: Cambie AQUÍ | AW2: VER NUESTROS COMBOS
A3: {=+HYPERLINK("#"&CELL("direccion",INDIRECT("'LISTA SABANA'!B"&C3)),INDEX('LISTA SABANA'!C:C,C3,1))} -> RESORTES LINEA FERRETERIA | B3: {=+HYPERLINK("#"&CELL("direccion",INDIRECT("'LISTA SABANA'!B"&E3)),INDEX('LISTA SABANA'!C:C,E3,1))} -> ARANDELAS DE ALUMINIO | C3: =+MATCH(D3,'LISTA SABANA'!C:C,0) -> 413 | D3: RESORTES LINEA FERRETERIA | E3: =+MATCH(F3,'LISTA SABANA'!C:C,0) -> 2009 | F3: ARANDELAS DE ALUMINIO | G3: Buscador: | H3: neu | I3: {=+HYPERLINK("#"&CELL("direccion",INDIRECT("'LISTA SABANA'!B"&IFERROR(VLOOKUP(IFERROR(VLOOKUP("*"&H3&"*",$A$2:$A$27,1,0),VLOOKUP("*"&H3&"*",$B$2:$B$27,1,0)),$B$2:$E$27,4,0),VLOOKUP(IFERROR(VLOOKUP("*"&H3&"*",$A$2:$A$27,1,0),VLOOKUP("*"&H3&"*",$B$2:$B$27,1,0)),$A$2:$C$27,3,0)))),IFERROR(VLOOKUP("*"&H3&"*",$A$2:$A$27,1,0),VLOOKUP("*"&H3&"*",$B$2:$B$27,1,0))&" - IR")} -> CONECTORES NEUMÁTICOS - IR | BE3: N° | BF3: Productos
A4: {=+HYPERLINK("#"&CELL("direccion",INDIRECT("'LISTA SABANA'!B"&C4)),INDEX('LISTA SABANA'!C:C,C4,1))} -> RESORTES LINEA COMPLEMENTARIA | B4: {=+HYPERLINK("#"&CELL("direccion",INDIRECT("'LISTA SABANA'!B"&E4)),INDEX('LISTA SABANA'!C:C,E4,1))} -> ARANDELAS DE FIBRA | C4: =+MATCH(D4,'LISTA SABANA'!C:C,0) -> 508 | D4: RESORTES LINEA COMPLEMENTARIA | E4: =+MATCH(F4,'LISTA SABANA'!C:C,0) -> 2037 | F4: ARANDELAS DE FIBRA | H4: BUSQUEDA RAPIDA POR PRODUCTO | BE4: {=+_xlfn._xlws.FILTER(Table_2[Numero],Table_2[Producto]=ÍNDICE!I7,)} -> 4 | BF4: {=+_xlfn.UNIQUE(Table_2[Producto])} -> PLASTICOS
A5: {=+HYPERLINK("#"&CELL("direccion",INDIRECT("'LISTA SABANA'!B"&C5)),INDEX('LISTA SABANA'!C:C,C5,1))} -> RESORTES LINEA PESADA | B5: {=+HYPERLINK("#"&CELL("direccion",INDIRECT("'LISTA SABANA'!B"&E5)),INDEX('LISTA SABANA'!C:C,E5,1))} -> ARANDELAS DE POLIPROPILENO | C5: =+MATCH(D5,'LISTA SABANA'!C:C,0) -> 622 | D5: RESORTES LINEA PESADA | E5: =+MATCH(F5,'LISTA SABANA'!C:C,0) -> 2069 | F5: ARANDELAS DE POLIPROPILENO | H5: Producto: | I5: CONECTORES NEUMÁTICOS | J5: Cambie AQUÍ | BE5: 5 | BF5: RESORTES LINEA FERRETERIA
A6: {=+HYPERLINK("#"&CELL("direccion",INDIRECT("'LISTA SABANA'!B"&C6)),INDEX('LISTA SABANA'!C:C,C6,1))} -> RESORTES LINEA BULONERA | B6: {=+HYPERLINK("#"&CELL("direccion",INDIRECT("'LISTA SABANA'!B"&E6)),INDEX('LISTA SABANA'!C:C,E6,1))} -> PICOS PARA GAS | C6: =+MATCH(D6,'LISTA SABANA'!C:C,0) -> 665 | D6: RESORTES LINEA BULONERA | E6: =+MATCH(F6,'LISTA SABANA'!C:C,0) -> 2363 | F6: PICOS PARA GAS | H6: N°: | I6: 98 | J6: Cambie AQUÍ | BE6: 6 | BF6: RESORTES LINEA COMPLEMENTARIA
A7: {=+HYPERLINK("#"&CELL("direccion",INDIRECT("'LISTA SABANA'!B"&C7)),INDEX('LISTA SABANA'!C:C,C7,1))} -> RESORTES LINEA AUTOMOTOR | B7: {=+HYPERLINK("#"&CELL("direccion",INDIRECT("'LISTA SABANA'!B"&E7)),INDEX('LISTA SABANA'!C:C,E7,1))} -> RETENES SEGURIDAD | C7: =+MATCH(D7,'LISTA SABANA'!C:C,0) -> 702 | D7: RESORTES LINEA AUTOMOTOR | E7: =+MATCH(F7,'LISTA SABANA'!C:C,0) -> 2419 | F7: RETENES SEGURIDAD | G7: 0 | H7: Producto: | I7: =+IFERROR(VLOOKUP("*"&I5&"*",$A$2:$A$27,1,0),VLOOKUP("*"&I5&"*",$B$2:$F$27,1,0)) -> CONECTORES NEUMÁTICOS | L7: =+I6 -> 98 | BE7: 8 | BF7: RESORTES LINEA PESADA
A8: {=+HYPERLINK("#"&CELL("direccion",INDIRECT("'LISTA SABANA'!B"&C8)),INDEX('LISTA SABANA'!C:C,C8,1))} -> RESORTES LINEA HORNO | B8: {=+HYPERLINK("#"&CELL("direccion",INDIRECT("'LISTA SABANA'!B"&E8)),INDEX('LISTA SABANA'!C:C,E8,1))} -> ARANLOCK | C8: =+MATCH(D8,'LISTA SABANA'!C:C,0) -> 800 | D8: RESORTES LINEA HORNO | E8: =+MATCH(F8,'LISTA SABANA'!C:C,0) -> 2435 | F8: ARANLOCK | H8: N° | I8: Descripción | J8: Lista $ | K8: Costo | L8: VENTA | BE8: 9 | BF8: RESORTES LINEA AUTOMOTOR
A9: {=+HYPERLINK("#"&CELL("direccion",INDIRECT("'LISTA SABANA'!B"&C9)),INDEX('LISTA SABANA'!C:C,C9,1))} -> ORING | B9: {=+HYPERLINK("#"&CELL("direccion",INDIRECT("'LISTA SABANA'!B"&E9)),INDEX('LISTA SABANA'!C:C,E9,1))} -> ESPARRAGOS DE ACERO | C9: =+MATCH(D9,'LISTA SABANA'!C:C,0) -> 828 | D9: ORING | E9: =+MATCH(F9,'LISTA SABANA'!C:C,0) -> 2449 | F9: ESPARRAGOS DE ACERO | H9: =+VLOOKUP(IFERROR(VLOOKUP("*"&I5&"*",$A$2:$A$27,1,0),VLOOKUP("*"&I5&"*",$B$2:$F$27,1,0))&I6&"*",BD!$A$2:$E$5000,3,0) -> 98 | I9: =+VLOOKUP(IFERROR(VLOOKUP("*"&I5&"*",$A$2:$A$27,1,0),VLOOKUP("*"&I5&"*",$B$2:$F$27,1,0))&I6&"*",BD!$A$2:$E$5000,4,0) -> Unión doble plástica 8 mm | J9: =+VLOOKUP(IFERROR(VLOOKUP("*"&I5&"*",$A$2:$A$27,1,0),VLOOKUP("*"&I5&"*",$B$2:$B$27,1,0))&I6&"*",BD!$A$2:$E$5000,5,0) -> 999.51 | K9: =+J9-(J9*DES.1) -> 539.7354 | L9: =+VLOOKUP(I7&H9,'LISTA SABANA'!A:I,9,0) -> 971.53 | BE9: 10 | BF9: RESORTES LINEA HORNO
A10: {=+HYPERLINK("#"&CELL("direccion",INDIRECT("'LISTA SABANA'!B"&C10)),INDEX('LISTA SABANA'!C:C,C10,1))} -> CARBONES | B10: {=+HYPERLINK("#"&CELL("direccion",INDIRECT("'LISTA SABANA'!B"&E10)),INDEX('LISTA SABANA'!C:C,E10,1))} -> PASACABLES DE GOMA | C10: =+MATCH(D10,'LISTA SABANA'!C:C,0) -> 978 | D10: CARBONES | E10: =+MATCH(F10,'LISTA SABANA'!C:C,0) -> 2507 | F10: PASACABLES DE GOMA | BE10: 11 | BF10: RESORTES LINEA BULONERA
A11: {=+HYPERLINK("#"&CELL("direccion",INDIRECT("'LISTA SABANA'!B"&C11)),INDEX('LISTA SABANA'!C:C,C11,1))} -> TERMINALES | B11: {=+HYPERLINK("#"&CELL("direccion",INDIRECT("'LISTA SABANA'!B"&E11)),INDEX('LISTA SABANA'!C:C,E11,1))} -> ALEMITES | C11: =+MATCH(D11,'LISTA SABANA'!C:C,0) -> 1037 | D11: TERMINALES | E11: =+MATCH(F11,'LISTA SABANA'!C:C,0) -> 2535 | F11: ALEMITES | BE11: 44 | BF11: SEEGER DIN 471
A12: {=+HYPERLINK("#"&CELL("direccion",INDIRECT("'LISTA SABANA'!B"&C12)),INDEX('LISTA SABANA'!C:C,C12,1))} -> REGATONES | B12: {=+HYPERLINK("#"&CELL("direccion",INDIRECT("'LISTA SABANA'!B"&E12)),INDEX('LISTA SABANA'!C:C,E12,1))} -> CONECTORES NEUMÁTICOS | C12: =+MATCH(D12,'LISTA SABANA'!C:C,0) -> 1121 | D12: REGATONES | E12: =+MATCH(F12,'LISTA SABANA'!C:C,0) -> 2559 | F12: CONECTORES NEUMÁTICOS | BE12: 45 | BF12: SEEGER DIN 472
A13: {=+HYPERLINK("#"&CELL("direccion",INDIRECT("'LISTA SABANA'!B"&C13)),INDEX('LISTA SABANA'!C:C,C13,1))} -> ARANDELAS DE GOMA | B13: {=+HYPERLINK("#"&CELL("direccion",INDIRECT("'LISTA SABANA'!B"&E13)),INDEX('LISTA SABANA'!C:C,E13,1))} -> CONECTORES NUEVA INCORPORACION | C13: =+MATCH(D13,'LISTA SABANA'!C:C,0) -> 1210 | D13: ARANDELAS DE GOMA | E13: =+MATCH(F13,'LISTA SABANA'!C:C,0) -> 2632 | F13: CONECTORES NUEVA INCORPORACION | H13: Fecha Ultima Actualización: | I13: 46140 | J13: Actualización, algunos precios DE LISTA | BE13: 46 | BF13: ORING
A14: {=+HYPERLINK("#"&CELL("direccion",INDIRECT("'LISTA SABANA'!B"&C14)),INDEX('LISTA SABANA'!C:C,C14,1))} -> ARANDELAS DE GOMA LINEA PESADA | B14: {=+HYPERLINK("#"&CELL("direccion",INDIRECT("'LISTA SABANA'!B"&E14)),INDEX('LISTA SABANA'!C:C,E14,1))} -> RACORD - ACOPLES - REDUCCIONES - ENTREROSCAS | C14: =+MATCH(D14,'LISTA SABANA'!C:C,0) -> 1264 | D14: ARANDELAS DE GOMA LINEA PESADA | E14: =+MATCH(F14,'LISTA SABANA'!C:C,0) -> 2682 | F14: RACORD - ACOPLES - REDUCCIONES - ENTREROSCAS | I14: Productos Afectados: | J14: ARANDELAS DE INYECCION | BE14: 47 | BF14: INSERTOS
A15: {=+HYPERLINK("#"&CELL("direccion",INDIRECT("'LISTA SABANA'!B"&C15)),INDEX('LISTA SABANA'!C:C,C15,1))} -> SEEGER DIN 471 | B15: {=+HYPERLINK("#"&CELL("direccion",INDIRECT("'LISTA SABANA'!B"&E15)),INDEX('LISTA SABANA'!C:C,E15,1))} -> TAPONES DE CARTER | C15: =+MATCH(D15,'LISTA SABANA'!C:C,0) -> 1293 | D15: SEEGER DIN 471 | E15: =+MATCH(F15,'LISTA SABANA'!C:C,0) -> 2744 | F15: TAPONES DE CARTER | J15: CONECTORES NEUMÁTICOS | BE15: 62 | BF15: CONEXIÓN DE CHAPA
A16: {=+HYPERLINK("#"&CELL("direccion",INDIRECT("'LISTA SABANA'!B"&C16)),INDEX('LISTA SABANA'!C:C,C16,1))} -> SEEGER DIN 472 | B16: {=+HYPERLINK("#"&CELL("direccion",INDIRECT("'LISTA SABANA'!B"&E16)),INDEX('LISTA SABANA'!C:C,E16,1))} -> ABRAZADERAS C/ GOMA - AC INOXIDABLE | C16: =+MATCH(D16,'LISTA SABANA'!C:C,0) -> 1355 | D16: SEEGER DIN 472 | E16: =+MATCH(F16,'LISTA SABANA'!C:C,0) -> 2771 | F16: ABRAZADERAS C/ GOMA - AC INOXIDABLE | J16: RESORTES LINEA PESADA | BE16: 63 | BF16: TOPES Y TAPONES DE GOMA
A17: {=+HYPERLINK("#"&CELL("direccion",INDIRECT("'LISTA SABANA'!B"&C17)),INDEX('LISTA SABANA'!C:C,C17,1))} -> INSERTOS | B17: {=+HYPERLINK("#"&CELL("direccion",INDIRECT("'LISTA SABANA'!B"&E17)),INDEX('LISTA SABANA'!C:C,E17,1))} -> ABRAZADERAS C/ GOMA - ALUMINIO | C17: =+MATCH(D17,'LISTA SABANA'!C:C,0) -> 1422 | D17: INSERTOS | E17: =+MATCH(F17,'LISTA SABANA'!C:C,0) -> 2790 | F17: ABRAZADERAS C/ GOMA - ALUMINIO | J17: REGATONES | BE17: 65 | BF17: CONECTORES PLASTICOS MANGUERAS
A18: {=+HYPERLINK("#"&CELL("direccion",INDIRECT("'LISTA SABANA'!B"&C18)),INDEX('LISTA SABANA'!C:C,C18,1))} -> TOPES Y TAPONES DE GOMA | B18: {=+HYPERLINK("#"&CELL("direccion",INDIRECT("'LISTA SABANA'!B"&E18)),INDEX('LISTA SABANA'!C:C,E18,1))} -> PERILLAS DE COCINA | C18: =+MATCH(D18,'LISTA SABANA'!C:C,0) -> 1449 | D18: TOPES Y TAPONES DE GOMA | E18: =+MATCH(F18,'LISTA SABANA'!C:C,0) -> 2809 | F18: PERILLAS DE COCINA | J18: TERMINALES | BE18: 66 | BF18: TUERCAS RAPIDAS
A19: {=+HYPERLINK("#"&CELL("direccion",INDIRECT("'LISTA SABANA'!B"&C19)),INDEX('LISTA SABANA'!C:C,C19,1))} -> CHAVETAS | B19: {=+HYPERLINK("#"&CELL("direccion",INDIRECT("'LISTA SABANA'!B"&E19)),INDEX('LISTA SABANA'!C:C,E19,1))} -> UNIONES ORIENTABLES | C19: =+MATCH(D19,'LISTA SABANA'!C:C,0) -> 1516 | D19: CHAVETAS | E19: =+MATCH(F19,'LISTA SABANA'!C:C,0) -> 2870 | F19: UNIONES ORIENTABLES | J19: RESORTES LINEA FERRETERIA | BE19: 67 | BF19: ARANDELAS DE COBRE
A20: {=+HYPERLINK("#"&CELL("direccion",INDIRECT("'LISTA SABANA'!B"&C20)),INDEX('LISTA SABANA'!C:C,C20,1))} -> GANCHOS - CHAVETAS | B20: {=+HYPERLINK("#"&CELL("direccion",INDIRECT("'LISTA SABANA'!B"&E20)),INDEX('LISTA SABANA'!C:C,E20,1))} -> ARANDELAS DE INYECCION | C20: =+MATCH(D20,'LISTA SABANA'!C:C,0) -> 1546 | D20: GANCHOS - CHAVETAS | E20: =+MATCH(F20,'LISTA SABANA'!C:C,0) -> 2910 | F20: ARANDELAS DE INYECCION | J20: CONECTORES NUEVA INCORPORACION | BE20: 68 | BF20: ARANDELAS DE ALUMINIO
A21: {=+HYPERLINK("#"&CELL("direccion",INDIRECT("'LISTA SABANA'!B"&C21)),INDEX('LISTA SABANA'!C:C,C21,1))} -> CHAVETAS PARTIDAS | B21: {=+HYPERLINK("#"&CELL("direccion",INDIRECT("'LISTA SABANA'!B"&E21)),INDEX('LISTA SABANA'!C:C,E21,1))} -> ACCESORIOS DE BRONCE UNION POLIAMIDA | C21: =+MATCH(D21,'LISTA SABANA'!C:C,0) -> 1571 | D21: CHAVETAS PARTIDAS | E21: =+MATCH(F21,'LISTA SABANA'!C:C,0) -> 2951 | F21: ACCESORIOS DE BRONCE UNION POLIAMIDA | J21: UNIONES ORIENTABLES | BE21: 77 | BF21: ARANDELAS DE FIBRA
A22: {=+HYPERLINK("#"&CELL("direccion",INDIRECT("'LISTA SABANA'!B"&C22)),INDEX('LISTA SABANA'!C:C,C22,1))} -> ESPINAS ELASTICAS | B22: {=+HYPERLINK("#"&CELL("direccion",INDIRECT("'LISTA SABANA'!B"&E22)),INDEX('LISTA SABANA'!C:C,E22,1))} -> INTERRUPTORES Y PULSADORES | C22: =+MATCH(D22,'LISTA SABANA'!C:C,0) -> 1608 | D22: ESPINAS ELASTICAS | E22: =+MATCH(F22,'LISTA SABANA'!C:C,0) -> 2985 | F22: INTERRUPTORES Y PULSADORES | J22: RESORTES LINEA COMPLEMENTARIA | BE22: 78 | BF22: ARANDELAS DE POLIPROPILENO
A23: {=+HYPERLINK("#"&CELL("direccion",INDIRECT("'LISTA SABANA'!B"&C23)),INDEX('LISTA SABANA'!C:C,C23,1))} -> CONEXIÓN DE ALUMINIO | B23: {=+HYPERLINK("#"&CELL("direccion",INDIRECT("'LISTA SABANA'!B"&E23)),INDEX('LISTA SABANA'!C:C,E23,1))} -> CLIPS IMPORTADOS | C23: =+MATCH(D23,'LISTA SABANA'!C:C,0) -> 1664 | D23: CONEXIÓN DE ALUMINIO | E23: =+MATCH(F23,'LISTA SABANA'!C:C,0) -> 3031 | F23: CLIPS IMPORTADOS | J23: RETENES SEGURIDAD | BE23: 79 | BF23: SUPLEMENTO 0,2
A24: {=+HYPERLINK("#"&CELL("direccion",INDIRECT("'LISTA SABANA'!B"&C24)),INDEX('LISTA SABANA'!C:C,C24,1))} -> CONEXIONES T EN ALUMINIO | B24: {=+HYPERLINK("#"&CELL("direccion",INDIRECT("'LISTA SABANA'!B"&E24)),INDEX('LISTA SABANA'!C:C,E24,1))} -> TORNILLERIA ESPECIAL | C24: =+MATCH(D24,'LISTA SABANA'!C:C,0) -> 1726 | D24: CONEXIONES T EN ALUMINIO | E24: =+MATCH(F24,'LISTA SABANA'!C:C,0) -> 3354 | F24: TORNILLERIA ESPECIAL | J24: ARANDELAS DE ALUMINIO | BE24: 80 | BF24: SUPLEMENTO 0,8
A25: {=+HYPERLINK("#"&CELL("direccion",INDIRECT("'LISTA SABANA'!B"&C25)),INDEX('LISTA SABANA'!C:C,C25,1))} -> CONECTORES PLASTICOS MANGUERAS | B25: {=+HYPERLINK("#"&CELL("direccion",INDIRECT("'LISTA SABANA'!B"&E25)),INDEX('LISTA SABANA'!C:C,E25,1))} -> TUERCAS RAPIDAS NUEVAS | C25: =+MATCH(D25,'LISTA SABANA'!C:C,0) -> 1810 | D25: CONECTORES PLASTICOS MANGUERAS | E25: =+MATCH(F25,'LISTA SABANA'!C:C,0) -> 3433 | F25: TUERCAS RAPIDAS NUEVAS | J25: TAPONES DE CARTER | BE25: 81 | BF25: RACORD - ACOPLES - REDUCCIONES - ENTREROSCAS
A26: {=+HYPERLINK("#"&CELL("direccion",INDIRECT("'LISTA SABANA'!B"&C26)),INDEX('LISTA SABANA'!C:C,C26,1))} -> TUERCAS RAPIDAS | B26: {=+HYPERLINK("#"&CELL("direccion",INDIRECT("'LISTA SABANA'!B"&E26)),INDEX('LISTA SABANA'!C:C,E26,1))} -> CONECTORES DE COMBUSTIBLE | C26: =+MATCH(D26,'LISTA SABANA'!C:C,0) -> 1887 | D26: TUERCAS RAPIDAS | E26: =+MATCH(F26,'LISTA SABANA'!C:C,0) -> 3470 | F26: CONECTORES DE COMBUSTIBLE | J26: ALEMITES | BE26: 86 | BF26: TERMINALES
... A28: {=+HYPERLINK("#"&CELL("direccion",INDIRECT("'LISTA SABANA'!B"&C28)),INDEX('LISTA SABANA'!C:C,C28,1))} -> TARUGOS ESTRIADOS | B28: {=+HYPERLINK("#"&CELL("direccion",INDIRECT("'LISTA SABANA'!B"&E28)),INDEX('LISTA SABANA'!C:C,E28,1))} -> SUPLEMENTO 0,8 | C28: =+MATCH(D28,'LISTA SABANA'!C:C,0) -> 1945 | D28: TARUGOS ESTRIADOS | E28: =+MATCH(F28,'LISTA SABANA'!C:C,0) -> 2256 | F28: SUPLEMENTO 0,8 | J28: CARBONES | BE28: 89 | BF28: ARANDELAS DE GOMA LINEA PESADA
J29: INSERTOS | BE29: 90 | BF29: CHAVETAS
J30: PLASTICOS | BE30: 91 | BF30: GANCHOS - CHAVETAS
J31: SUPLEMENTO 0,2 | BE31: 92 | BF31: CARBONES
J32: SUPLEMENTO 0,8 | BE32: 97 | BF32: ESPINAS ELASTICAS
J33: SEEGER DIN 472 | BE33: 98 | BF33: TARUGOS ESTRIADOS
J34: ESPARRAGOS DE ACERO | BE34: 99 | BF34: RETENES SEGURIDAD
J35: RACORD - ACOPLES - REDUCCIONES - ENTREROSCAS | BE35: 100 | BF35: ARANLOCK
J36: RESORTES LINEA BULONERA | BE36: 101 | BF36: ESPARRAGOS DE ACERO
J37: PERILLAS DE COCINA | BE37: 108 | BF37: PASACABLES DE GOMA
J38: INTERRUPTORES Y PULSADORES | BE38: 109 | BF38: CHAVETAS PARTIDAS
J39: CONECTORES PLASTICOS MANGUERAS | BE39: 110 | BF39: ALEMITES
J40: CONECTORES DE COMBUSTIBLE | BE40: 111 | BF40: CONECTORES NEUMÁTICOS
BE41: 140 | BF41: CONECTORES NUEVA INCORPORACION
BE42: 141 | BF42: PICOS PARA GAS
BE43: 142 | BF43: REGATONES
BE44: 143 | BF44: TAPONES DE CARTER
BE45: 153 | BF45: ABRAZADERAS C/ GOMA - AC INOXIDABLE
BE46: 154 | BF46: ABRAZADERAS C/ GOMA - ALUMINIO
BE47: 155 | BF47: TUERCAS REMACHES
BE48: 157 | BF48: PERILLAS DE COCINA
BE49: 158 | BF49: CONEXIÓN DE ALUMINIO
BE50: 159 | BF50: CONEXIONES T EN ALUMINIO
BE51: 160 | BF51: UNIONES ORIENTABLES
BE52: 197 | BF52: ARANDELAS DE INYECCION
... BE58: 207 | BF58: CONECTORES DE COMBUSTIBLE
BE59: 211
BE60: 212
BE61: 213
BE62: 219
BE63: 220
BE64: 221
BE65: 222
BE66: 124
BE67: 125
BE68: 126
BE69: 127
BE70: 228
... BE75: 51
BE76: Gaveta

Sheet LISTA SABANA
J1: Volver al
J2: Indice
D3: Fecha Última Actualización: | E3: =+ÍNDICE!I13 -> 46140
C5: FABRICA Y DISTRIBUIDORA MAXIFER | G5: Agregar IVA? | L5: * *
G7: NO
L8: * *
C11: LISTA SABANA | G11: Descuento: | I11: VENTA | L11: * *
C12: NUMERO | D12: DESCRIPCIÓN | E12: Precio de Lista | G12: 0.46 | I12: 0.8
A14: 1 | C14: =+VLOOKUP(A14,BD!$G:$H,2,0) -> PLASTICOS
A15: PLASTICOS1 | C15: =+VLOOKUP(A15,BD!$A$2:$E$3988,3,0) -> 1 | D15: =+VLOOKUP(A15,BD!$A$2:$E$3988,4,0) -> Grampa tapizado R11- R18 | E15: =+VLOOKUP(A15,BD!$A$2:$E$3988,5,0) -> 1159.02 | G15: =IF($G$7="SI",ROUND(E15-(E15*DES.1),2)*1.21,ROUND(E15-(E15*DES.1),2)) -> 625.87 | I15: {=+ROUND(G15+(G15*DES.2),2)} -> 1126.57 | O15: =+IFERROR(VLOOKUP(A15,Imagen!A:B,2,0),"") -> http://http2.mlstatic.com/D_708492-MLA72045130481_102023-F.jpg
A16: PLASTICOS2 | C16: =+VLOOKUP(A16,BD!$A$2:$E$3988,3,0) -> 2 | D16: =+VLOOKUP(A16,BD!$A$2:$E$3988,4,0) -> Grampa tapizadoDuna-128-147 | E16: =+VLOOKUP(A16,BD!$A$2:$E$3988,5,0) -> 578.93 | G16: =IF($G$7="SI",ROUND(E16-(E16*DES.1),2)*1.21,ROUND(E16-(E16*DES.1),2)) -> 312.62 | I16: {=+ROUND(G16+(G16*DES.2),2)} -> 562.72 | O16: =+IFERROR(VLOOKUP(A16,Imagen!A:B,2,0),"") -> http://http2.mlstatic.com/D_785905-MLA71988387406_102023-F.jpg
A17: PLASTICOS3 | C17: =+VLOOKUP(A17,BD!$A$2:$E$3988,3,0) -> 3 | D17: =+VLOOKUP(A17,BD!$A$2:$E$3988,4,0) -> Tuerca autorros. FIAT-RENAULT | E17: =+VLOOKUP(A17,BD!$A$2:$E$3988,5,0) -> 629.53 | G17: =IF($G$7="SI",ROUND(E17-(E17*DES.1),2)*1.21,ROUND(E17-(E17*DES.1),2)) -> 339.95 | I17: {=+ROUND(G17+(G17*DES.2),2)} -> 611.91 | O17: =+IFERROR(VLOOKUP(A17,Imagen!A:B,2,0),"") -> http://http2.mlstatic.com/D_878027-MLA72239756252_102023-F.jpg
A18: PLASTICOS4 | C18: =+VLOOKUP(A18,BD!$A$2:$E$3988,3,0) -> 4 | D18: =+VLOOKUP(A18,BD!$A$2:$E$3988,4,0) -> Fijacion consola GACELL | E18: =+VLOOKUP(A18,BD!$A$2:$E$3988,5,0) -> 654.85 | G18: =IF($G$7="SI",ROUND(E18-(E18*DES.1),2)*1.21,ROUND(E18-(E18*DES.1),2)) -> 353.62 | I18: {=+ROUND(G18+(G18*DES.2),2)} -> 636.52 | O18: =+IFERROR(VLOOKUP(A18,Imagen!A:B,2,0),"") -> http://http2.mlstatic.com/D_741302-MLA71988387408_102023-F.jpg
A19: PLASTICOS5 | C19: =+VLOOKUP(A19,BD!$A$2:$E$3988,3,0) -> 5 | D19: =+VLOOKUP(A19,BD!$A$2:$E$3988,4,0) -> Fijacion OPTICA 128 | E19: =+VLOOKUP(A19,BD!$A$2:$E$3988,5,0) -> 727.61 | G19: =IF($G$7="SI",ROUND(E19-(E19*DES.1),2)*1.21,ROUND(E19-(E19*DES.1),2)) -> 392.91 | I19: {=+ROUND(G19+(G19*DES.2),2)} -> 707.24 | O19: =+IFERROR(VLOOKUP(A19,Imagen!A:B,2,0),"") -> http://http2.mlstatic.com/D_986792-MLA72240891774_102023-F.jpg
A20: PLASTICOS6 | C20: =+VLOOKUP(A20,BD!$A$2:$E$3988,3,0) -> 6 | D20: =+VLOOKUP(A20,BD!$A$2:$E$3988,4,0) -> Tuerca autorros. GACELL | E20: =+VLOOKUP(A20,BD!$A$2:$E$3988,5,0) -> 914.71 | G20: =IF($G$7="SI",ROUND(E20-(E20*DES.1),2)*1.21,ROUND(E20-(E20*DES.1),2)) -> 493.94 | I20: {=+ROUND(G20+(G20*DES.2),2)} -> 889.09 | O20: =+IFERROR(VLOOKUP(A20,Imagen!A:B,2,0),"") -> http://http2.mlstatic.com/D_953256-MLA71988435968_102023-F.jpg
A21: PLASTICOS7 | C21: =+VLOOKUP(A21,BD!$A$2:$E$3988,3,0) -> 7 | D21: =+VLOOKUP(A21,BD!$A$2:$E$3988,4,0) -> Fijacion patente FIAT | E21: =+VLOOKUP(A21,BD!$A$2:$E$3988,5,0) -> 578.93 | G21: =IF($G$7="SI",ROUND(E21-(E21*DES.1),2)*1.21,ROUND(E21-(E21*DES.1),2)) -> 312.62 | I21: {=+ROUND(G21+(G21*DES.2),2)} -> 562.72 | O21: =+IFERROR(VLOOKUP(A21,Imagen!A:B,2,0),"") -> http://http2.mlstatic.com/D_778884-MLA71988387412_102023-F.jpg
A22: PLASTICOS8 | C22: =+VLOOKUP(A22,BD!$A$2:$E$3988,3,0) -> 8 | D22: =+VLOOKUP(A22,BD!$A$2:$E$3988,4,0) -> Registro faro 125 | E22: =+VLOOKUP(A22,BD!$A$2:$E$3988,5,0) -> 654.85 | G22: =IF($G$7="SI",ROUND(E22-(E22*DES.1),2)*1.21,ROUND(E22-(E22*DES.1),2)) -> 353.62 | I22: {=+ROUND(G22+(G22*DES.2),2)} -> 636.52 | O22: =+IFERROR(VLOOKUP(A22,Imagen!A:B,2,0),"") -> http://http2.mlstatic.com/D_881846-MLA71988387472_102023-F.jpg
A23: PLASTICOS9 | C23: =+VLOOKUP(A23,BD!$A$2:$E$3988,3,0) -> 9 | D23: =+VLOOKUP(A23,BD!$A$2:$E$3988,4,0) -> Tuerca autorroscante FIAT | E23: =+VLOOKUP(A23,BD!$A$2:$E$3988,5,0) -> 680.9 | G23: =IF($G$7="SI",ROUND(E23-(E23*DES.1),2)*1.21,ROUND(E23-(E23*DES.1),2)) -> 367.69 | I23: {=+ROUND(G23+(G23*DES.2),2)} -> 661.84 | O23: =+IFERROR(VLOOKUP(A23,Imagen!A:B,2,0),"") -> http://http2.mlstatic.com/D_647342-MLA72293218763_102023-F.jpg
A24: PLASTICOS10 | C24: =+VLOOKUP(A24,BD!$A$2:$E$3988,3,0) -> 10 | D24: =+VLOOKUP(A24,BD!$A$2:$E$3988,4,0) -> Fijacion capot 125 | E24: =+VLOOKUP(A24,BD!$A$2:$E$3988,5,0) -> 771.26 | G24: =IF($G$7="SI",ROUND(E24-(E24*DES.1),2)*1.21,ROUND(E24-(E24*DES.1),2)) -> 416.48 | I24: {=+ROUND(G24+(G24*DES.2),2)} -> 749.66 | O24: =+IFERROR(VLOOKUP(A24,Imagen!A:B,2,0),"") -> http://http2.mlstatic.com/D_724144-MLA72292952705_102023-F.jpg
A25: PLASTICOS11 | C25: =+VLOOKUP(A25,BD!$A$2:$E$3988,3,0) -> 11 | D25: =+VLOOKUP(A25,BD!$A$2:$E$3988,4,0) -> Tuerca parrilla DUNA- UNO | E25: =+VLOOKUP(A25,BD!$A$2:$E$3988,5,0) -> 917.77 | G25: =IF($G$7="SI",ROUND(E25-(E25*DES.1),2)*1.21,ROUND(E25-(E25*DES.1),2)) -> 495.6 | I25: {=+ROUND(G25+(G25*DES.2),2)} -> 892.08 | O25: =+IFERROR(VLOOKUP(A25,Imagen!A:B,2,0),"") -> http://http2.mlstatic.com/D_790405-MLA72292952961_102023-F.jpg
A26: PLASTICOS12 | C26: =+VLOOKUP(A26,BD!$A$2:$E$3988,3,0) -> 12 | D26: =+VLOOKUP(A26,BD!$A$2:$E$3988,4,0) -> Tuerca autorroc. PEUGEOT | E26: =+VLOOKUP(A26,BD!$A$2:$E$3988,5,0) -> 933.24 | G26: =IF($G$7="SI",ROUND(E26-(E26*DES.1),2)*1.21,ROUND(E26-(E26*DES.1),2)) -> 503.95 | I26: {=+ROUND(G26+(G26*DES.2),2)} -> 907.11 | O26: =+IFERROR(VLOOKUP(A26,Imagen!A:B,2,0),"") -> http://http2.mlstatic.com/D_780043-MLA72292972855_102023-F.jpg
... A412: PLASTICOS402 | C412: =+VLOOKUP(A412,BD!$A$2:$E$3988,3,0) -> 402 | D412: =+VLOOKUP(A412,BD!$A$2:$E$3988,4,0) -> fijación paragolpes y pasaruedas toyota hilux, corrolla, etios | E412: =+VLOOKUP(A412,BD!$A$2:$E$3988,5,0) -> 2127.79 | G412: =IF($G$7="SI",ROUND(E412-(E412*DES.1),2)*1.21,ROUND(E412-(E412*DES.1),2)) -> 1149.01 | I412: {=+ROUND(G412+(G412*DES.2),2)} -> 2068.22 | O412: =+IFERROR(VLOOKUP(A412,Imagen!A:B,2,0),"")
A413: =+A14+1 -> 2 | C413: =+VLOOKUP(A413,BD!$G:$H,2,0) -> RESORTES LINEA FERRETERIA | O413: =+IFERROR(VLOOKUP(A413,Imagen!A:B,2,0),"")
A414: RESORTES LINEA FERRETERIA1 | C414: =+VLOOKUP(A414,BD!$A$2:$E$3988,3,0) -> 1 | D414: =+VLOOKUP(A414,BD!$A$2:$E$3988,4,0) -> 0,5 x 4,5 x 30 - Expansión | E414: =+VLOOKUP(A414,BD!$A$2:$E$3988,5,0) -> 1128 | G414: =IF($G$7="SI",ROUND(E414-(E414*DES.1),2)*1.21,ROUND(E414-(E414*DES.1),2)) -> 609.12 | I414: {=+ROUND(G414+(G414*DES.2),2)} -> 1096.42 | O414: =+IFERROR(VLOOKUP(A414,Imagen!A:B,2,0),"") -> http://http2.mlstatic.com/D_625707-MLA72113085111_102023-F.jpg
A415: RESORTES LINEA FERRETERIA2 | C415: =+VLOOKUP(A415,BD!$A$2:$E$3988,3,0) -> 2 | D415: =+VLOOKUP(A415,BD!$A$2:$E$3988,4,0) -> 0,5 x 6 x 50 - Expansión | E415: =+VLOOKUP(A415,BD!$A$2:$E$3988,5,0) -> 1361.26 | G415: =IF($G$7="SI",ROUND(E415-(E415*DES.1),2)*1.21,ROUND(E415-(E415*DES.1),2)) -> 735.08 | I415: {=+ROUND(G415+(G415*DES.2),2)} -> 1323.14 | O415: =+IFERROR(VLOOKUP(A415,Imagen!A:B,2,0),"") -> http://http2.mlstatic.com/D_854113-MLA72113085113_102023-F.jpg
A416: RESORTES LINEA FERRETERIA3 | C416: =+VLOOKUP(A416,BD!$A$2:$E$3988,3,0) -> 3 | D416: =+VLOOKUP(A416,BD!$A$2:$E$3988,4,0) -> 0,6 x 7 x 30 - Expansión | E416: =+VLOOKUP(A416,BD!$A$2:$E$3988,5,0) -> 1128 | G416: =IF($G$7="SI",ROUND(E416-(E416*DES.1),2)*1.21,ROUND(E416-(E416*DES.1),2)) -> 609.12 | I416: {=+ROUND(G416+(G416*DES.2),2)} -> 1096.42 | O416: =+IFERROR(VLOOKUP(A416,Imagen!A:B,2,0),"") -> http://http2.mlstatic.com/D_989357-MLA72112882997_102023-F.jpg
A417: RESORTES LINEA FERRETERIA4 | C417: =+VLOOKUP(A417,BD!$A$2:$E$3988,3,0) -> 4 | D417: =+VLOOKUP(A417,BD!$A$2:$E$3988,4,0) -> 0,6 x 8 x 50 - Expansión | E417: =+VLOOKUP(A417,BD!$A$2:$E$3988,5,0) -> 1112.12 | G417: =IF($G$7="SI",ROUND(E417-(E417*DES.1),2)*1.21,ROUND(E417-(E417*DES.1),2)) -> 600.54 | I417: {=+ROUND(G417+(G417*DES.2),2)} -> 1080.97 | O417: =+IFERROR(VLOOKUP(A417,Imagen!A:B,2,0),"") -> http://http2.mlstatic.com/D_890937-MLA72112834605_102023-F.jpg
A418: RESORTES LINEA FERRETERIA5 | C418: =+VLOOKUP(A418,BD!$A$2:$E$3988,3,0) -> 5 | D418: =+VLOOKUP(A418,BD!$A$2:$E$3988,4,0) -> 0,8 x 6 x 50 - Expansión | E418: =+VLOOKUP(A418,BD!$A$2:$E$3988,5,0) -> 1112.12 | G418: =IF($G$7="SI",ROUND(E418-(E418*DES.1),2)*1.21,ROUND(E418-(E418*DES.1),2)) -> 600.54 | I418: {=+ROUND(G418+(G418*DES.2),2)} -> 1080.97 | O418: =+IFERROR(VLOOKUP(A418,Imagen!A:B,2,0),"") -> http://http2.mlstatic.com/D_721810-MLA72113085115_102023-F.jpg
A419: RESORTES LINEA FERRETERIA6 | C419: =+VLOOKUP(A419,BD!$A$2:$E$3988,3,0) -> 6 | D419: =+VLOOKUP(A419,BD!$A$2:$E$3988,4,0) -> 0,8 x 8 x 50 - Expansión | E419: =+VLOOKUP(A419,BD!$A$2:$E$3988,5,0) -> 1165.72 | G419: =IF($G$7="SI",ROUND(E419-(E419*DES.1),2)*1.21,ROUND(E419-(E419*DES.1),2)) -> 629.49 | I419: {=+ROUND(G419+(G419*DES.2),2)} -> 1133.08 | O419: =+IFERROR(VLOOKUP(A419,Imagen!A:B,2,0),"") -> http://http2.mlstatic.com/D_839781-MLA72053880672_102023-F.jpg
A420: RESORTES LINEA FERRETERIA7 | C420: =+VLOOKUP(A420,BD!$A$2:$E$3988,3,0) -> 7 | D420: =+VLOOKUP(A420,BD!$A$2:$E$3988,4,0) -> 0,8 x 10 x 50 - Expansión | E420: =+VLOOKUP(A420,BD!$A$2:$E$3988,5,0) -> 1378.67 | G420: =IF($G$7="SI",ROUND(E420-(E420*DES.1),2)*1.21,ROUND(E420-(E420*DES.1),2)) -> 744.48 | I420: {=+ROUND(G420+(G420*DES.2),2)} -> 1340.06 | O420: =+IFERROR(VLOOKUP(A420,Imagen!A:B,2,0),"") -> http://http2.mlstatic.com/D_708588-MLA72112834607_102023-F.jpg
A421: RESORTES LINEA FERRETERIA8 | C421: =+VLOOKUP(A421,BD!$A$2:$E$3988,3,0) -> 8 | D421: =+VLOOKUP(A421,BD!$A$2:$E$3988,4,0) -> 0,8 x 10 x 100 - Expansión | E421: =+VLOOKUP(A421,BD!$A$2:$E$3988,5,0) -> 2116.64 | G421: =IF($G$7="SI",ROUND(E421-(E421*DES.1),2)*1.21,ROUND(E421-(E421*DES.1),2)) -> 1142.99 | I421: {=+ROUND(G421+(G421*DES.2),2)} -> 2057.38 | O421: =+IFERROR(VLOOKUP(A421,Imagen!A:B,2,0),"") -> http://http2.mlstatic.com/D_790933-MLA72112961125_102023-F.jpg
A422: RESORTES LINEA FERRETERIA9 | C422: =+VLOOKUP(A422,BD!$A$2:$E$3988,3,0) -> 9 | D422: =+VLOOKUP(A422,BD!$A$2:$E$3988,4,0) -> 1 x 8 x 40 - Expansión | E422: =+VLOOKUP(A422,BD!$A$2:$E$3988,5,0) -> 1632.32 | G422: =IF($G$7="SI",ROUND(E422-(E422*DES.1),2)*1.21,ROUND(E422-(E422*DES.1),2)) -> 881.45 | I422: {=+ROUND(G422+(G422*DES.2),2)} -> 1586.61 | O422: =+IFERROR(VLOOKUP(A422,Imagen!A:B,2,0),"") -> http://http2.mlstatic.com/D_843566-MLA72053883038_102023-F.jpg
A423: RESORTES LINEA FERRETERIA10 | C423: =+VLOOKUP(A423,BD!$A$2:$E$3988,3,0) -> 10 | D423: =+VLOOKUP(A423,BD!$A$2:$E$3988,4,0) -> 1 x 8 x 100 - Expansión | E423: =+VLOOKUP(A423,BD!$A$2:$E$3988,5,0) -> 2331.84 | G423: =IF($G$7="SI",ROUND(E423-(E423*DES.1),2)*1.21,ROUND(E423-(E423*DES.1),2)) -> 1259.19 | I423: {=+ROUND(G423+(G423*DES.2),2)} -> 2266.54 | O423: =+IFERROR(VLOOKUP(A423,Imagen!A:B,2,0),"") -> http://http2.mlstatic.com/D_930418-MLA72112834643_102023-F.jpg
A424: RESORTES LINEA FERRETERIA11 | C424: =+VLOOKUP(A424,BD!$A$2:$E$3988,3,0) -> 11 | D424: =+VLOOKUP(A424,BD!$A$2:$E$3988,4,0) -> 1 x 10 x 70 - Expansión | E424: =+VLOOKUP(A424,BD!$A$2:$E$3988,5,0) -> 2331.84 | G424: =IF($G$7="SI",ROUND(E424-(E424*DES.1),2)*1.21,ROUND(E424-(E424*DES.1),2)) -> 1259.19 | I424: {=+ROUND(G424+(G424*DES.2),2)} -> 2266.54 | O424: =+IFERROR(VLOOKUP(A424,Imagen!A:B,2,0),"") -> http://http2.mlstatic.com/D_929167-MLA72112834641_102023-F.jpg
A425: RESORTES LINEA FERRETERIA12 | C425: =+VLOOKUP(A425,BD!$A$2:$E$3988,3,0) -> 12 | D425: =+VLOOKUP(A425,BD!$A$2:$E$3988,4,0) -> 1 x 10 x 120 - Expansión | E425: =+VLOOKUP(A425,BD!$A$2:$E$3988,5,0) -> 2690.44 | G425: =IF($G$7="SI",ROUND(E425-(E425*DES.1),2)*1.21,ROUND(E425-(E425*DES.1),2)) -> 1452.84 | I425: {=+ROUND(G425+(G425*DES.2),2)} -> 2615.11 | O425: =+IFERROR(VLOOKUP(A425,Imagen!A:B,2,0),"") -> http://http2.mlstatic.com/D_687934-MLA72112834645_102023-F.jpg
... A507: RESORTES LINEA FERRETERIA103 | C507: =+VLOOKUP(A507,BD!$A$2:$E$3988,3,0) -> 103 | D507: =+VLOOKUP(A507,BD!$A$2:$E$3988,4,0) -> 1,5 x 11 x 20 - Compresión | E507: =+VLOOKUP(A507,BD!$A$2:$E$3988,5,0) -> 940 | G507: =IF($G$7="SI",ROUND(E507-(E507*DES.1),2)*1.21,ROUND(E507-(E507*DES.1),2)) -> 507.6 | I507: {=+ROUND(G507+(G507*DES.2),2)} -> 913.68 | O507: =+IFERROR(VLOOKUP(A507,Imagen!A:B,2,0),"") -> http://http2.mlstatic.com/D_781113-MLA72112883873_102023-F.jpg
A508: =+A413+1 -> 3 | C508: =+VLOOKUP(A508,BD!$G:$H,2,0) -> RESORTES LINEA COMPLEMENTARIA | O508: =+IFERROR(VLOOKUP(A508,Imagen!A:B,2,0),"")
A509: RESORTES LINEA COMPLEMENTARIA269 | C509: =+VLOOKUP(A509,BD!$A$2:$E$3988,3,0) -> 269 | D509: =+VLOOKUP(A509,BD!$A$2:$E$3988,4,0) -> TIJERA PODAR - Expansión | E509: =+VLOOKUP(A509,BD!$A$2:$E$3988,5,0) -> 3408.08 | G509: =IF($G$7="SI",ROUND(E509-(E509*DES.1),2)*1.21,ROUND(E509-(E509*DES.1),2)) -> 1840.36 | I509: {=+ROUND(G509+(G509*DES.2),2)} -> 3312.65 | O509: =+IFERROR(VLOOKUP(A509,Imagen!A:B,2,0),"")
A510: RESORTES LINEA COMPLEMENTARIA270 | C510: =+VLOOKUP(A510,BD!$A$2:$E$3988,3,0) -> 270 | D510: =+VLOOKUP(A510,BD!$A$2:$E$3988,4,0) -> 0,3 x 3 x 15 - Expansión | E510: =+VLOOKUP(A510,BD!$A$2:$E$3988,5,0) -> 933.16 | G510: =IF($G$7="SI",ROUND(E510-(E510*DES.1),2)*1.21,ROUND(E510-(E510*DES.1),2)) -> 503.91 | I510: {=+ROUND(G510+(G510*DES.2),2)} -> 907.04 | O510: =+IFERROR(VLOOKUP(A510,Imagen!A:B,2,0),"") -> http://http2.mlstatic.com/D_910001-MLA72112884111_102023-F.jpg
A511: RESORTES LINEA COMPLEMENTARIA271 | C511: =+VLOOKUP(A511,BD!$A$2:$E$3988,3,0) -> 271 | D511: =+VLOOKUP(A511,BD!$A$2:$E$3988,4,0) -> 0,3 x 4,5 x 22 - Expansión | E511: =+VLOOKUP(A511,BD!$A$2:$E$3988,5,0) -> 933.16 | G511: =IF($G$7="SI",ROUND(E511-(E511*DES.1),2)*1.21,ROUND(E511-(E511*DES.1),2)) -> 503.91 | I511: {=+ROUND(G511+(G511*DES.2),2)} -> 907.04 | O511: =+IFERROR(VLOOKUP(A511,Imagen!A:B,2,0),"") -> http://http2.mlstatic.com/D_642975-MLA72113086249_102023-F.jpg
A512: RESORTES LINEA COMPLEMENTARIA272 | C512: =+VLOOKUP(A512,BD!$A$2:$E$3988,3,0) -> 272 | D512: =+VLOOKUP(A512,BD!$A$2:$E$3988,4,0) -> 0,3 x 4,2 x 15 - Expansión | E512: =+VLOOKUP(A512,BD!$A$2:$E$3988,5,0) -> 933.16 | G512: =IF($G$7="SI",ROUND(E512-(E512*DES.1),2)*1.21,ROUND(E512-(E512*DES.1),2)) -> 503.91 | I512: {=+ROUND(G512+(G512*DES.2),2)} -> 907.04 | O512: =+IFERROR(VLOOKUP(A512,Imagen!A:B,2,0),"") -> http://http2.mlstatic.com/D_621147-MLA72112884121_102023-F.jpg
A513: RESORTES LINEA COMPLEMENTARIA273 | C513: =+VLOOKUP(A513,BD!$A$2:$E$3988,3,0) -> 273 | D513: =+VLOOKUP(A513,BD!$A$2:$E$3988,4,0) -> 0,5 x 4,5 x 80 - Expansión | E513: =+VLOOKUP(A513,BD!$A$2:$E$3988,5,0) -> 1512.52 | G513: =IF($G$7="SI",ROUND(E513-(E513*DES.1),2)*1.21,ROUND(E513-(E513*DES.1),2)) -> 816.76 | I513: {=+ROUND(G513+(G513*DES.2),2)} -> 1470.17 | O513: =+IFERROR(VLOOKUP(A513,Imagen!A:B,2,0),"") -> http://http2.mlstatic.com/D_706724-MLA72113086257_102023-F.jpg
A514: RESORTES LINEA COMPLEMENTARIA274 | C514: =+VLOOKUP(A514,BD!$A$2:$E$3988,3,0) -> 274 | D514: =+VLOOKUP(A514,BD!$A$2:$E$3988,4,0) -> 0,5 x 6 x 60 - Expansión | E514: =+VLOOKUP(A514,BD!$A$2:$E$3988,5,0) -> 1378.67 | G514: =IF($G$7="SI",ROUND(E514-(E514*DES.1),2)*1.21,ROUND(E514-(E514*DES.1),2)) -> 744.48 | I514: {=+ROUND(G514+(G514*DES.2),2)} -> 1340.06 | O514: =+IFERROR(VLOOKUP(A514,Imagen!A:B,2,0),"") -> http://http2.mlstatic.com/D_785058-MLA72112884125_102023-F.jpg
A515: RESORTES LINEA COMPLEMENTARIA275 | C515: =+VLOOKUP(A515,BD!$A$2:$E$3988,3,0) -> 275 | D515: =+VLOOKUP(A515,BD!$A$2:$E$3988,4,0) -> 0,8 x 8 x 100 - Expansión | E515: =+VLOOKUP(A515,BD!$A$2:$E$3988,5,0) -> 1883.36 | G515: =IF($G$7="SI",ROUND(E515-(E515*DES.1),2)*1.21,ROUND(E515-(E515*DES.1),2)) -> 1017.01 | I515: {=+ROUND(G515+(G515*DES.2),2)} -> 1830.62 | O515: =+IFERROR(VLOOKUP(A515,Imagen!A:B,2,0),"") -> http://http2.mlstatic.com/D_895173-MLA72053955814_102023-F.jpg
A516: RESORTES LINEA COMPLEMENTARIA276 | C516: =+VLOOKUP(A516,BD!$A$2:$E$3988,3,0) -> 276 | D516: =+VLOOKUP(A516,BD!$A$2:$E$3988,4,0) -> 1 x 10 x 95 - Expansión | E516: =+VLOOKUP(A516,BD!$A$2:$E$3988,5,0) -> 2511.12 | G516: =IF($G$7="SI",ROUND(E516-(E516*DES.1),2)*1.21,ROUND(E516-(E516*DES.1),2)) -> 1356 | I516: {=+ROUND(G516+(G516*DES.2),2)} -> 2440.8 | O516: =+IFERROR(VLOOKUP(A516,Imagen!A:B,2,0),"") -> http://http2.mlstatic.com/D_743772-MLA72053881904_102023-F.jpg
A517: RESORTES LINEA COMPLEMENTARIA277 | C517: =+VLOOKUP(A517,BD!$A$2:$E$3988,3,0) -> 277 | D517: =+VLOOKUP(A517,BD!$A$2:$E$3988,4,0) -> 1 x 10 x 144 - Expansión | E517: =+VLOOKUP(A517,BD!$A$2:$E$3988,5,0) -> 3138.92 | G517: =IF($G$7="SI",ROUND(E517-(E517*DES.1),2)*1.21,ROUND(E517-(E517*DES.1),2)) -> 1695.02 | I517: {=+ROUND(G517+(G517*DES.2),2)} -> 3051.04 | O517: =+IFERROR(VLOOKUP(A517,Imagen!A:B,2,0),"") -> http://http2.mlstatic.com/D_763347-MLA72113086291_102023-F.jpg
A518: RESORTES LINEA COMPLEMENTARIA278 | C518: =+VLOOKUP(A518,BD!$A$2:$E$3988,3,0) -> 278 | D518: =+VLOOKUP(A518,BD!$A$2:$E$3988,4,0) -> 1 x 13 x 50 - Expansión | E518: =+VLOOKUP(A518,BD!$A$2:$E$3988,5,0) -> 1883.36 | G518: =IF($G$7="SI",ROUND(E518-(E518*DES.1),2)*1.21,ROUND(E518-(E518*DES.1),2)) -> 1017.01 | I518: {=+ROUND(G518+(G518*DES.2),2)} -> 1830.62 | O518: =+IFERROR(VLOOKUP(A518,Imagen!A:B,2,0),"") -> http://http2.mlstatic.com/D_693791-MLA72112962297_102023-F.jpg
A519: RESORTES LINEA COMPLEMENTARIA279 | C519: =+VLOOKUP(A519,BD!$A$2:$E$3988,3,0) -> 279 | D519: =+VLOOKUP(A519,BD!$A$2:$E$3988,4,0) -> 1 x 13 x 95 - Expansión | E519: =+VLOOKUP(A519,BD!$A$2:$E$3988,5,0) -> 2959.6 | G519: =IF($G$7="SI",ROUND(E519-(E519*DES.1),2)*1.21,ROUND(E519-(E519*DES.1),2)) -> 1598.18 | I519: {=+ROUND(G519+(G519*DES.2),2)} -> 2876.72 | O519: =+IFERROR(VLOOKUP(A519,Imagen!A:B,2,0),"") -> http://http2.mlstatic.com/D_656529-MLA72112962301_102023-F.jpg
A520: RESORTES LINEA COMPLEMENTARIA280 | C520: =+VLOOKUP(A520,BD!$A$2:$E$3988,3,0) -> 280 | D520: =+VLOOKUP(A520,BD!$A$2:$E$3988,4,0) -> 1 x 13 x 177 - Expansión | E520: =+VLOOKUP(A520,BD!$A$2:$E$3988,5,0) -> 4125.32 | G520: =IF($G$7="SI",ROUND(E520-(E520*DES.1),2)*1.21,ROUND(E520-(E520*DES.1),2)) -> 2227.67 | I520: {=+ROUND(G520+(G520*DES.2),2)} -> 4009.81 | O520: =+IFERROR(VLOOKUP(A520,Imagen!A:B,2,0),"") -> http://http2.mlstatic.com/D_679257-MLA72113086299_102023-F.jpg
... A621: RESORTES LINEA COMPLEMENTARIA411 | C621: =+VLOOKUP(A621,BD!$A$2:$E$3988,3,0) -> 411 | D621: =+VLOOKUP(A621,BD!$A$2:$E$3988,4,0) -> 1,50 - Torsión | E621: =+VLOOKUP(A621,BD!$A$2:$E$3988,5,0) -> 1989.4 | G621: =IF($G$7="SI",ROUND(E621-(E621*DES.1),2)*1.21,ROUND(E621-(E621*DES.1),2)) -> 1074.28 | I621: {=+ROUND(G621+(G621*DES.2),2)} -> 1933.7 | O621: =+IFERROR(VLOOKUP(A621,Imagen!A:B,2,0),"")
A622: =+A508+1 -> 4 | C622: =+VLOOKUP(A622,BD!$G:$H,2,0) -> RESORTES LINEA PESADA | O622: =+IFERROR(VLOOKUP(A622,Imagen!A:B,2,0),"")
A623: RESORTES LINEA PESADA110 | C623: =+VLOOKUP(A623,BD!$A$2:$E$3988,3,0) -> 110 | D623: =+VLOOKUP(A623,BD!$A$2:$E$3988,4,0) -> 2 x 12 x 150 - Compresión | E623: =+VLOOKUP(A623,BD!$A$2:$E$3988,5,0) -> 2836.12 | G623: =IF($G$7="SI",ROUND(E623-(E623*DES.1),2)*1.21,ROUND(E623-(E623*DES.1),2)) -> 1531.5 | I623: {=+ROUND(G623+(G623*DES.2),2)} -> 2756.7 | O623: =+IFERROR(VLOOKUP(A623,Imagen!A:B,2,0),"") -> http://http2.mlstatic.com/D_995011-MLA72053881652_102023-F.jpg
A624: RESORTES LINEA PESADA112 | C624: =+VLOOKUP(A624,BD!$A$2:$E$3988,3,0) -> 112 | D624: =+VLOOKUP(A624,BD!$A$2:$E$3988,4,0) -> 2 x 18 x 130 - Compresión | E624: =+VLOOKUP(A624,BD!$A$2:$E$3988,5,0) -> 2836.12 | G624: =IF($G$7="SI",ROUND(E624-(E624*DES.1),2)*1.21,ROUND(E624-(E624*DES.1),2)) -> 1531.5 | I624: {=+ROUND(G624+(G624*DES.2),2)} -> 2756.7 | O624: =+IFERROR(VLOOKUP(A624,Imagen!A:B,2,0),"") -> http://http2.mlstatic.com/D_792846-MLA72053881658_102023-F.jpg
A625: RESORTES LINEA PESADA114 | C625: =+VLOOKUP(A625,BD!$A$2:$E$3988,3,0) -> 114 | D625: =+VLOOKUP(A625,BD!$A$2:$E$3988,4,0) -> 2 x 20 x 100 - Compresión | E625: =+VLOOKUP(A625,BD!$A$2:$E$3988,5,0) -> 2448.28 | G625: =IF($G$7="SI",ROUND(E625-(E625*DES.1),2)*1.21,ROUND(E625-(E625*DES.1),2)) -> 1322.07 | I625: {=+ROUND(G625+(G625*DES.2),2)} -> 2379.73 | O625: =+IFERROR(VLOOKUP(A625,Imagen!A:B,2,0),"") -> http://http2.mlstatic.com/D_709038-MLA72112962033_102023-F.jpg
A626: RESORTES LINEA PESADA116 | C626: =+VLOOKUP(A626,BD!$A$2:$E$3988,3,0) -> 116 | D626: =+VLOOKUP(A626,BD!$A$2:$E$3988,4,0) -> 2 x 25 x 100 - Compresión | E626: =+VLOOKUP(A626,BD!$A$2:$E$3988,5,0) -> 2645.72 | G626: =IF($G$7="SI",ROUND(E626-(E626*DES.1),2)*1.21,ROUND(E626-(E626*DES.1),2)) -> 1428.69 | I626: {=+ROUND(G626+(G626*DES.2),2)} -> 2571.64 | O626: =+IFERROR(VLOOKUP(A626,Imagen!A:B,2,0),"") -> http://http2.mlstatic.com/D_640435-MLA72053881668_102023-F.jpg
A627: RESORTES LINEA PESADA118 | C627: =+VLOOKUP(A627,BD!$A$2:$E$3988,3,0) -> 118 | D627: =+VLOOKUP(A627,BD!$A$2:$E$3988,4,0) -> 2 x 30 x 50 - Compresión | E627: =+VLOOKUP(A627,BD!$A$2:$E$3988,5,0) -> 2170.24 | G627: =IF($G$7="SI",ROUND(E627-(E627*DES.1),2)*1.21,ROUND(E627-(E627*DES.1),2)) -> 1171.93 | I627: {=+ROUND(G627+(G627*DES.2),2)} -> 2109.47 | O627: =+IFERROR(VLOOKUP(A627,Imagen!A:B,2,0),"") -> http://http2.mlstatic.com/D_761339-MLA72112883897_102023-F.jpg
A628: RESORTES LINEA PESADA120 | C628: =+VLOOKUP(A628,BD!$A$2:$E$3988,3,0) -> 120 | D628: =+VLOOKUP(A628,BD!$A$2:$E$3988,4,0) -> 2 x 30 x 100 - Compresión | E628: =+VLOOKUP(A628,BD!$A$2:$E$3988,5,0) -> 2869.76 | G628: =IF($G$7="SI",ROUND(E628-(E628*DES.1),2)*1.21,ROUND(E628-(E628*DES.1),2)) -> 1549.67 | I628: {=+ROUND(G628+(G628*DES.2),2)} -> 2789.41 | O628: =+IFERROR(VLOOKUP(A628,Imagen!A:B,2,0),"")
A629: RESORTES LINEA PESADA122 | C629: =+VLOOKUP(A629,BD!$A$2:$E$3988,3,0) -> 122 | D629: =+VLOOKUP(A629,BD!$A$2:$E$3988,4,0) -> 2 x 34 x 42 - Compresión | E629: =+VLOOKUP(A629,BD!$A$2:$E$3988,5,0) -> 2170.24 | G629: =IF($G$7="SI",ROUND(E629-(E629*DES.1),2)*1.21,ROUND(E629-(E629*DES.1),2)) -> 1171.93 | I629: {=+ROUND(G629+(G629*DES.2),2)} -> 2109.47 | O629: =+IFERROR(VLOOKUP(A629,Imagen!A:B,2,0),"") -> http://http2.mlstatic.com/D_872690-MLA72112962049_102023-F.jpg
A630: RESORTES LINEA PESADA124 | C630: =+VLOOKUP(A630,BD!$A$2:$E$3988,3,0) -> 124 | D630: =+VLOOKUP(A630,BD!$A$2:$E$3988,4,0) -> 2,25 x 27 x 37 - Compresión | E630: =+VLOOKUP(A630,BD!$A$2:$E$3988,5,0) -> 2170.24 | G630: =IF($G$7="SI",ROUND(E630-(E630*DES.1),2)*1.21,ROUND(E630-(E630*DES.1),2)) -> 1171.93 | I630: {=+ROUND(G630+(G630*DES.2),2)} -> 2109.47 | O630: =+IFERROR(VLOOKUP(A630,Imagen!A:B,2,0),"") -> http://http2.mlstatic.com/D_969505-MLA72053955592_102023-F.jpg
A631: RESORTES LINEA PESADA125 | C631: =+VLOOKUP(A631,BD!$A$2:$E$3988,3,0) -> 125 | D631: =+VLOOKUP(A631,BD!$A$2:$E$3988,4,0) -> 2,5 x 17 x 35 - Compresión | E631: =+VLOOKUP(A631,BD!$A$2:$E$3988,5,0) -> 2170.24 | G631: =IF($G$7="SI",ROUND(E631-(E631*DES.1),2)*1.21,ROUND(E631-(E631*DES.1),2)) -> 1171.93 | I631: {=+ROUND(G631+(G631*DES.2),2)} -> 2109.47 | O631: =+IFERROR(VLOOKUP(A631,Imagen!A:B,2,0),"")
A632: RESORTES LINEA PESADA126 | C632: =+VLOOKUP(A632,BD!$A$2:$E$3988,3,0) -> 126 | D632: =+VLOOKUP(A632,BD!$A$2:$E$3988,4,0) -> 2,5 x 25 x 55 - Compresión | E632: =+VLOOKUP(A632,BD!$A$2:$E$3988,5,0) -> 2466.4 | G632: =IF($G$7="SI",ROUND(E632-(E632*DES.1),2)*1.21,ROUND(E632-(E632*DES.1),2)) -> 1331.86 | I632: {=+ROUND(G632+(G632*DES.2),2)} -> 2397.35 | O632: =+IFERROR(VLOOKUP(A632,Imagen!A:B,2,0),"") -> http://http2.mlstatic.com/D_763527-MLA72112883917_102023-F.jpg
A633: RESORTES LINEA PESADA128 | C633: =+VLOOKUP(A633,BD!$A$2:$E$3988,3,0) -> 128 | D633: =+VLOOKUP(A633,BD!$A$2:$E$3988,4,0) -> 2,5 x 33 x 50 - Compresión | E633: =+VLOOKUP(A633,BD!$A$2:$E$3988,5,0) -> 2636.84 | G633: =IF($G$7="SI",ROUND(E633-(E633*DES.1),2)*1.21,ROUND(E633-(E633*DES.1),2)) -> 1423.89 | I633: {=+ROUND(G633+(G633*DES.2),2)} -> 2563 | O633: =+IFERROR(VLOOKUP(A633,Imagen!A:B,2,0),"") -> http://http2.mlstatic.com/D_835254-MLA72112883933_102023-F.jpg
A634: RESORTES LINEA PESADA130 | C634: =+VLOOKUP(A634,BD!$A$2:$E$3988,3,0) -> 130 | D634: =+VLOOKUP(A634,BD!$A$2:$E$3988,4,0) -> 2,5 x 37 x 50 - Compresión | E634: =+VLOOKUP(A634,BD!$A$2:$E$3988,5,0) -> 2780.28 | G634: =IF($G$7="SI",ROUND(E634-(E634*DES.1),2)*1.21,ROUND(E634-(E634*DES.1),2)) -> 1501.35 | I634: {=+ROUND(G634+(G634*DES.2),2)} -> 2702.43 | O634: =+IFERROR(VLOOKUP(A634,Imagen!A:B,2,0),"") -> http://http2.mlstatic.com/D_856532-MLA72113086077_102023-F.jpg
... A664: RESORTES LINEA PESADA198 | C664: =+VLOOKUP(A664,BD!$A$2:$E$3988,3,0) -> 198 | D664: =+VLOOKUP(A664,BD!$A$2:$E$3988,4,0) -> 5 x 39 x 200 - Espansión | E664: =+VLOOKUP(A664,BD!$A$2:$E$3988,5,0) -> 22420.92 | G664: =IF($G$7="SI",ROUND(E664-(E664*DES.1),2)*1.21,ROUND(E664-(E664*DES.1),2)) -> 12107.3 | I664: {=+ROUND(G664+(G664*DES.2),2)} -> 21793.14 | O664: =+IFERROR(VLOOKUP(A664,Imagen!A:B,2,0),"") -> http://http2.mlstatic.com/D_709190-MLA72113086239_102023-F.jpg
A665: =+A622+1 -> 5 | C665: =+VLOOKUP(A665,BD!$G:$H,2,0) -> RESORTES LINEA BULONERA | O665: =+IFERROR(VLOOKUP(A665,Imagen!A:B,2,0),"")
A666: RESORTES LINEA BULONERA800 | C666: =+VLOOKUP(A666,BD!$A$2:$E$3988,3,0) -> 800 | D666: =+VLOOKUP(A666,BD!$A$2:$E$3988,4,0) -> EXPANSION - 0,8 x 8 L.: 195 mm | E666: =+VLOOKUP(A666,BD!$A$2:$E$3988,5,0) -> 3321.33 | G666: =IF($G$7="SI",ROUND(E666-(E666*DES.1),2)*1.21,ROUND(E666-(E666*DES.1),2)) -> 1793.52 | I666: {=+ROUND(G666+(G666*DES.2),2)} -> 3228.34 | O666: =+IFERROR(VLOOKUP(A666,Imagen!A:B,2,0),"") -> http://http2.mlstatic.com/D_850306-MLA72527836320_102023-F.jpg
A667: RESORTES LINEA BULONERA801 | C667: =+VLOOKUP(A667,BD!$A$2:$E$3988,3,0) -> 801 | D667: =+VLOOKUP(A667,BD!$A$2:$E$3988,4,0) -> EXPANSION - 0,8 x 10 L.: 195 mm | E667: =+VLOOKUP(A667,BD!$A$2:$E$3988,5,0) -> 3321.33 | G667: =IF($G$7="SI",ROUND(E667-(E667*DES.1),2)*1.21,ROUND(E667-(E667*DES.1),2)) -> 1793.52 | I667: {=+ROUND(G667+(G667*DES.2),2)} -> 3228.34 | O667: =+IFERROR(VLOOKUP(A667,Imagen!A:B,2,0),"") -> http://http2.mlstatic.com/D_988591-MLA72597560377_102023-F.jpg
A668: RESORTES LINEA BULONERA803 | C668: =+VLOOKUP(A668,BD!$A$2:$E$3988,3,0) -> 803 | D668: =+VLOOKUP(A668,BD!$A$2:$E$3988,4,0) -> EXPANSION - 1 x 11 L.: 195 mm | E668: =+VLOOKUP(A668,BD!$A$2:$E$3988,5,0) -> 3321.33 | G668: =IF($G$7="SI",ROUND(E668-(E668*DES.1),2)*1.21,ROUND(E668-(E668*DES.1),2)) -> 1793.52 | I668: {=+ROUND(G668+(G668*DES.2),2)} -> 3228.34 | O668: =+IFERROR(VLOOKUP(A668,Imagen!A:B,2,0),"") -> http://http2.mlstatic.com/D_623680-MLA72597619343_102023-F.jpg
A669: RESORTES LINEA BULONERA805 | C669: =+VLOOKUP(A669,BD!$A$2:$E$3988,3,0) -> 805 | D669: =+VLOOKUP(A669,BD!$A$2:$E$3988,4,0) -> EXPANSION - 1 x 14 L.: 195 mm | E669: =+VLOOKUP(A669,BD!$A$2:$E$3988,5,0) -> 3265.92 | G669: =IF($G$7="SI",ROUND(E669-(E669*DES.1),2)*1.21,ROUND(E669-(E669*DES.1),2)) -> 1763.6 | I669: {=+ROUND(G669+(G669*DES.2),2)} -> 3174.48 | O669: =+IFERROR(VLOOKUP(A669,Imagen!A:B,2,0),"") -> http://http2.mlstatic.com/D_741980-MLA72527462798_102023-F.jpg
A670: RESORTES LINEA BULONERA807 | C670: =+VLOOKUP(A670,BD!$A$2:$E$3988,3,0) -> 807 | D670: =+VLOOKUP(A670,BD!$A$2:$E$3988,4,0) -> EXPANSION - 1,25 x 14 L.: 195 mm | E670: =+VLOOKUP(A670,BD!$A$2:$E$3988,5,0) -> 3732.48 | G670: =IF($G$7="SI",ROUND(E670-(E670*DES.1),2)*1.21,ROUND(E670-(E670*DES.1),2)) -> 2015.54 | I670: {=+ROUND(G670+(G670*DES.2),2)} -> 3627.97 | O670: =+IFERROR(VLOOKUP(A670,Imagen!A:B,2,0),"") -> http://http2.mlstatic.com/D_873468-MLA72527836318_102023-F.jpg
A671: RESORTES LINEA BULONERA808 | C671: =+VLOOKUP(A671,BD!$A$2:$E$3988,3,0) -> 808 | D671: =+VLOOKUP(A671,BD!$A$2:$E$3988,4,0) -> EXPANSION - 1,25 x 16 L.: 195 mm | E671: =+VLOOKUP(A671,BD!$A$2:$E$3988,5,0) -> 4888 | G671: =IF($G$7="SI",ROUND(E671-(E671*DES.1),2)*1.21,ROUND(E671-(E671*DES.1),2)) -> 2639.52 | I671: {=+ROUND(G671+(G671*DES.2),2)} -> 4751.14 | O671: =+IFERROR(VLOOKUP(A671,Imagen!A:B,2,0),"") -> http://http2.mlstatic.com/D_850306-MLA72527836320_102023-F.jpg
A672: RESORTES LINEA BULONERA809 | C672: =+VLOOKUP(A672,BD!$A$2:$E$3988,3,0) -> 809 | D672: =+VLOOKUP(A672,BD!$A$2:$E$3988,4,0) -> EXPANSION - 1,5 x 15 L.: 196 mm | E672: =+VLOOKUP(A672,BD!$A$2:$E$3988,5,0) -> 5054.4 | G672: =IF($G$7="SI",ROUND(E672-(E672*DES.1),2)*1.21,ROUND(E672-(E672*DES.1),2)) -> 2729.38 | I672: {=+ROUND(G672+(G672*DES.2),2)} -> 4912.88 | O672: =+IFERROR(VLOOKUP(A672,Imagen!A:B,2,0),"") -> http://http2.mlstatic.com/D_971341-MLA72527906028_102023-F.jpg
A673: RESORTES LINEA BULONERA810 | C673: =+VLOOKUP(A673,BD!$A$2:$E$3988,3,0) -> 810 | D673: =+VLOOKUP(A673,BD!$A$2:$E$3988,4,0) -> EXPANSION - 1,5 x 17 L.: 195 mm | E673: =+VLOOKUP(A673,BD!$A$2:$E$3988,5,0) -> 5054.4 | G673: =IF($G$7="SI",ROUND(E673-(E673*DES.1),2)*1.21,ROUND(E673-(E673*DES.1),2)) -> 2729.38 | I673: {=+ROUND(G673+(G673*DES.2),2)} -> 4912.88 | O673: =+IFERROR(VLOOKUP(A673,Imagen!A:B,2,0),"") -> http://http2.mlstatic.com/D_850306-MLA72527836320_102023-F.jpg
A674: RESORTES LINEA BULONERA812 | C674: =+VLOOKUP(A674,BD!$A$2:$E$3988,3,0) -> 812 | D674: =+VLOOKUP(A674,BD!$A$2:$E$3988,4,0) -> EXPANSION - 1,5 x 20 L.: 195 mm | E674: =+VLOOKUP(A674,BD!$A$2:$E$3988,5,0) -> 6220.8 | G674: =IF($G$7="SI",ROUND(E674-(E674*DES.1),2)*1.21,ROUND(E674-(E674*DES.1),2)) -> 3359.23 | I674: {=+ROUND(G674+(G674*DES.2),2)} -> 6046.61 | O674: =+IFERROR(VLOOKUP(A674,Imagen!A:B,2,0),"") -> http://http2.mlstatic.com/D_850306-MLA72527836320_102023-F.jpg
A675: RESORTES LINEA BULONERA813 | C675: =+VLOOKUP(A675,BD!$A$2:$E$3988,3,0) -> 813 | D675: =+VLOOKUP(A675,BD!$A$2:$E$3988,4,0) -> EXPANSION - 1,75 x 14 L.: 196 mm | E675: =+VLOOKUP(A675,BD!$A$2:$E$3988,5,0) -> 5365.44 | G675: =IF($G$7="SI",ROUND(E675-(E675*DES.1),2)*1.21,ROUND(E675-(E675*DES.1),2)) -> 2897.34 | I675: {=+ROUND(G675+(G675*DES.2),2)} -> 5215.21 | O675: =+IFERROR(VLOOKUP(A675,Imagen!A:B,2,0),"") -> http://http2.mlstatic.com/D_850306-MLA72527836320_102023-F.jpg
A676: RESORTES LINEA BULONERA814 | C676: =+VLOOKUP(A676,BD!$A$2:$E$3988,3,0) -> 814 | D676: =+VLOOKUP(A676,BD!$A$2:$E$3988,4,0) -> EXPANSION - 1,75 x 16 L.: 195 mm | E676: =+VLOOKUP(A676,BD!$A$2:$E$3988,5,0) -> 5765.33 | G676: =IF($G$7="SI",ROUND(E676-(E676*DES.1),2)*1.21,ROUND(E676-(E676*DES.1),2)) -> 3113.28 | I676: {=+ROUND(G676+(G676*DES.2),2)} -> 5603.9 | O676: =+IFERROR(VLOOKUP(A676,Imagen!A:B,2,0),"") -> http://http2.mlstatic.com/D_850306-MLA72527836320_102023-F.jpg
A677: RESORTES LINEA BULONERA815 | C677: =+VLOOKUP(A677,BD!$A$2:$E$3988,3,0) -> 815 | D677: =+VLOOKUP(A677,BD!$A$2:$E$3988,4,0) -> EXPANSION - 1,75 x 18 L.: 195 mm | E677: =+VLOOKUP(A677,BD!$A$2:$E$3988,5,0) -> 5832 | G677: =IF($G$7="SI",ROUND(E677-(E677*DES.1),2)*1.21,ROUND(E677-(E677*DES.1),2)) -> 3149.28 | I677: {=+ROUND(G677+(G677*DES.2),2)} -> 5668.7 | O677: =+IFERROR(VLOOKUP(A677,Imagen!A:B,2,0),"") -> http://http2.mlstatic.com/D_850306-MLA72527836320_102023-F.jpg
... A701: RESORTES LINEA BULONERA872 | C701: =+VLOOKUP(A701,BD!$A$2:$E$3988,3,0) -> 872 | D701: =+VLOOKUP(A701,BD!$A$2:$E$3988,4,0) -> COMPRESION - 2 x 35 L.: 195 mm | E701: =+VLOOKUP(A701,BD!$A$2:$E$3988,5,0) -> 4888 | G701: =IF($G$7="SI",ROUND(E701-(E701*DES.1),2)*1.21,ROUND(E701-(E701*DES.1),2)) -> 2639.52 | I701: {=+ROUND(G701+(G701*DES.2),2)} -> 4751.14 | O701: =+IFERROR(VLOOKUP(A701,Imagen!A:B,2,0),"") -> http://http2.mlstatic.com/D_850306-MLA72527836320_102023-F.jpg
A702: =+A665+1 -> 6 | C702: =+VLOOKUP(A702,BD!$G:$H,2,0) -> RESORTES LINEA AUTOMOTOR | O702: =+IFERROR(VLOOKUP(A702,Imagen!A:B,2,0),"")
A703: RESORTES LINEA AUTOMOTOR400 | C703: =+VLOOKUP(A703,BD!$A$2:$E$3988,3,0) -> 400 | D703: =+VLOOKUP(A703,BD!$A$2:$E$3988,4,0) -> RESORTES LINEA FIAT - RESORTE SUPERIOR P/ZAPATAS FRENO TRAS.-FIAT 1500/1600/125/MULTICARGA | E703: =+VLOOKUP(A703,BD!$A$2:$E$3988,5,0) -> 4633.33 | G703: =IF($G$7="SI",ROUND(E703-(E703*DES.1),2)*1.21,ROUND(E703-(E703*DES.1),2)) -> 2502 | I703: {=+ROUND(G703+(G703*DES.2),2)} -> 4503.6 | O703: =+IFERROR(VLOOKUP(A703,Imagen!A:B,2,0),"")
A704: RESORTES LINEA AUTOMOTOR401 | C704: =+VLOOKUP(A704,BD!$A$2:$E$3988,3,0) -> 401 | D704: =+VLOOKUP(A704,BD!$A$2:$E$3988,4,0) -> RESORTES LINEA FIAT - RESORTE INFERIOR P/ZAPATAS FRENO TRAS.-FIAT 1500/1600/125/MULTICARGA | E704: =+VLOOKUP(A704,BD!$A$2:$E$3988,5,0) -> 5127.56 | G704: =IF($G$7="SI",ROUND(E704-(E704*DES.1),2)*1.21,ROUND(E704-(E704*DES.1),2)) -> 2768.88 | I704: {=+ROUND(G704+(G704*DES.2),2)} -> 4983.98 | O704: =+IFERROR(VLOOKUP(A704,Imagen!A:B,2,0),"")
A705: RESORTES LINEA AUTOMOTOR402 | C705: =+VLOOKUP(A705,BD!$A$2:$E$3988,3,0) -> 402 | D705: =+VLOOKUP(A705,BD!$A$2:$E$3988,4,0) -> RESORTES LINEA FIAT - RESORTE SUPERIOR P/ZAPATAS FRENO - FIAT 600 TRAS./DEL.-FIAT 128 TRAS. | E705: =+VLOOKUP(A705,BD!$A$2:$E$3988,5,0) -> 3397.78 | G705: =IF($G$7="SI",ROUND(E705-(E705*DES.1),2)*1.21,ROUND(E705-(E705*DES.1),2)) -> 1834.8 | I705: {=+ROUND(G705+(G705*DES.2),2)} -> 3302.64 | O705: =+IFERROR(VLOOKUP(A705,Imagen!A:B,2,0),"")
A706: RESORTES LINEA AUTOMOTOR405 | C706: =+VLOOKUP(A706,BD!$A$2:$E$3988,3,0) -> 405 | D706: =+VLOOKUP(A706,BD!$A$2:$E$3988,4,0) -> RESORTES LINEA FIAT - RESORTE P/PEDAL DE ACCION. EMBRAGUE- FIAT 600/128 | E706: =+VLOOKUP(A706,BD!$A$2:$E$3988,5,0) -> 5745.33 | G706: =IF($G$7="SI",ROUND(E706-(E706*DES.1),2)*1.21,ROUND(E706-(E706*DES.1),2)) -> 3102.48 | I706: {=+ROUND(G706+(G706*DES.2),2)} -> 5584.46 | O706: =+IFERROR(VLOOKUP(A706,Imagen!A:B,2,0),"")
A707: RESORTES LINEA AUTOMOTOR406 | C707: =+VLOOKUP(A707,BD!$A$2:$E$3988,3,0) -> 406 | D707: =+VLOOKUP(A707,BD!$A$2:$E$3988,4,0) -> RESORTES LINEA FIAT - RESORTE P/PALANCA DE CAJA DE VELOCIDADES FIAT 128 | E707: =+VLOOKUP(A707,BD!$A$2:$E$3988,5,0) -> 1853.33 | G707: =IF($G$7="SI",ROUND(E707-(E707*DES.1),2)*1.21,ROUND(E707-(E707*DES.1),2)) -> 1000.8 | I707: {=+ROUND(G707+(G707*DES.2),2)} -> 1801.44 | O707: =+IFERROR(VLOOKUP(A707,Imagen!A:B,2,0),"")
A708: RESORTES LINEA AUTOMOTOR409 | C708: =+VLOOKUP(A708,BD!$A$2:$E$3988,3,0) -> 409 | D708: =+VLOOKUP(A708,BD!$A$2:$E$3988,4,0) -> RESORTES LINEA FIAT - RESORTE P/CILINDRO MAESTRO DE FRENO. FIAT 1500/1600/125/MULTICARGA | E708: =+VLOOKUP(A708,BD!$A$2:$E$3988,5,0) -> 4015.56 | G708: =IF($G$7="SI",ROUND(E708-(E708*DES.1),2)*1.21,ROUND(E708-(E708*DES.1),2)) -> 2168.4 | I708: {=+ROUND(G708+(G708*DES.2),2)} -> 3903.12 | O708: =+IFERROR(VLOOKUP(A708,Imagen!A:B,2,0),"")
A709: RESORTES LINEA AUTOMOTOR414 | C709: =+VLOOKUP(A709,BD!$A$2:$E$3988,3,0) -> 414 | D709: =+VLOOKUP(A709,BD!$A$2:$E$3988,4,0) -> RESORTES LINEA FIAT - SEGURO ANTIRRUIDO P/PAST.F/ A DISCO FIAT 1500/1600/125/MULTICARGA | E709: =+VLOOKUP(A709,BD!$A$2:$E$3988,5,0) -> 1359.11 | G709: =IF($G$7="SI",ROUND(E709-(E709*DES.1),2)*1.21,ROUND(E709-(E709*DES.1),2)) -> 733.92 | I709: {=+ROUND(G709+(G709*DES.2),2)} -> 1321.06 | O709: =+IFERROR(VLOOKUP(A709,Imagen!A:B,2,0),"")
A710: RESORTES LINEA AUTOMOTOR415 | C710: =+VLOOKUP(A710,BD!$A$2:$E$3988,3,0) -> 415 | D710: =+VLOOKUP(A710,BD!$A$2:$E$3988,4,0) -> RESORTES LINEA FIAT - SEGURO P/PERNO PASADOR PAST. F/ A DISCO FIAT 1500/1600/125/MULTICARGA | E710: =+VLOOKUP(A710,BD!$A$2:$E$3988,5,0) -> 864.89 | G710: =IF($G$7="SI",ROUND(E710-(E710*DES.1),2)*1.21,ROUND(E710-(E710*DES.1),2)) -> 467.04 | I710: {=+ROUND(G710+(G710*DES.2),2)} -> 840.67 | O710: =+IFERROR(VLOOKUP(A710,Imagen!A:B,2,0),"")
A711: RESORTES LINEA AUTOMOTOR420 | C711: =+VLOOKUP(A711,BD!$A$2:$E$3988,3,0) -> 420 | D711: =+VLOOKUP(A711,BD!$A$2:$E$3988,4,0) -> RESORTES LINEA FIAT - RESORTE P/COMANDO DE ACELERADOR FIAT 600/770/800/133 | E711: =+VLOOKUP(A711,BD!$A$2:$E$3988,5,0) -> 7413.33 | G711: =IF($G$7="SI",ROUND(E711-(E711*DES.1),2)*1.21,ROUND(E711-(E711*DES.1),2)) -> 4003.2 | I711: {=+ROUND(G711+(G711*DES.2),2)} -> 7205.76 | O711: =+IFERROR(VLOOKUP(A711,Imagen!A:B,2,0),"")
A712: RESORTES LINEA AUTOMOTOR421 | C712: =+VLOOKUP(A712,BD!$A$2:$E$3988,3,0) -> 421 | D712: =+VLOOKUP(A712,BD!$A$2:$E$3988,4,0) -> RESORTES LINEA FIAT - CLIP P/CABLE COMANDO DE FRENO - FIAT 128 | E712: =+VLOOKUP(A712,BD!$A$2:$E$3988,5,0) -> 0 | G712: =IF($G$7="SI",ROUND(E712-(E712*DES.1),2)*1.21,ROUND(E712-(E712*DES.1),2)) -> 0 | I712: {=+ROUND(G712+(G712*DES.2),2)} -> 0 | O712: =+IFERROR(VLOOKUP(A712,Imagen!A:B,2,0),"")
A713: RESORTES LINEA AUTOMOTOR429 | C713: =+VLOOKUP(A713,BD!$A$2:$E$3988,3,0) -> 429 | D713: =+VLOOKUP(A713,BD!$A$2:$E$3988,4,0) -> RESORTES LINEA FIAT - RESORTE P/RETORNO DE PEDAL DE EMBRAGUE - FIAT 1600/125 | E713: =+VLOOKUP(A713,BD!$A$2:$E$3988,5,0) -> 8587.11 | G713: =IF($G$7="SI",ROUND(E713-(E713*DES.1),2)*1.21,ROUND(E713-(E713*DES.1),2)) -> 4637.04 | I713: {=+ROUND(G713+(G713*DES.2),2)} -> 8346.67 | O713: =+IFERROR(VLOOKUP(A713,Imagen!A:B,2,0),"")
A714: RESORTES LINEA AUTOMOTOR440 | C714: =+VLOOKUP(A714,BD!$A$2:$E$3988,3,0) -> 440 | D714: =+VLOOKUP(A714,BD!$A$2:$E$3988,4,0) -> RESORTES LINEA FIAT - RESORTE P/REGISTRO DER.-FIAT PALIO/SIENA | E714: =+VLOOKUP(A714,BD!$A$2:$E$3988,5,0) -> 3768.44 | G714: =IF($G$7="SI",ROUND(E714-(E714*DES.1),2)*1.21,ROUND(E714-(E714*DES.1),2)) -> 2034.96 | I714: {=+ROUND(G714+(G714*DES.2),2)} -> 3662.93 | O714: =+IFERROR(VLOOKUP(A714,Imagen!A:B,2,0),"")
... A799: RESORTES LINEA AUTOMOTOR797 | C799: =+VLOOKUP(A799,BD!$A$2:$E$3988,3,0) -> 797 | D799: =+VLOOKUP(A799,BD!$A$2:$E$3988,4,0) -> UNIVERSALES - RESORTE ACELERADOR UNIVERSAL MEDIANO | E799: =+VLOOKUP(A799,BD!$A$2:$E$3988,5,0) -> 2239.76 | G799: =IF($G$7="SI",ROUND(E799-(E799*DES.1),2)*1.21,ROUND(E799-(E799*DES.1),2)) -> 1209.47 | I799: {=+ROUND(G799+(G799*DES.2),2)} -> 2177.05 | O799: =+IFERROR(VLOOKUP(A799,Imagen!A:B,2,0),"")
A800: =+A702+1 -> 7 | C800: =+VLOOKUP(A800,BD!$G:$H,2,0) -> RESORTES LINEA HORNO | O800: =+IFERROR(VLOOKUP(A800,Imagen!A:B,2,0),"")
A801: RESORTES LINEA HORNO200 | C801: =+VLOOKUP(A801,BD!$A$2:$E$3988,3,0) -> 200 | D801: =+VLOOKUP(A801,BD!$A$2:$E$3988,4,0) -> LONGVIE L 4 - 1,5 mm - 15 mm - 210 mm | E801: =+VLOOKUP(A801,BD!$A$2:$E$3988,5,0) -> 4011.48 | G801: =IF($G$7="SI",ROUND(E801-(E801*DES.1),2)*1.21,ROUND(E801-(E801*DES.1),2)) -> 2166.2 | I801: {=+ROUND(G801+(G801*DES.2),2)} -> 3899.16 | O801: =+IFERROR(VLOOKUP(A801,Imagen!A:B,2,0),"")
A802: RESORTES LINEA HORNO203 | C802: =+VLOOKUP(A802,BD!$A$2:$E$3988,3,0) -> 203 | D802: =+VLOOKUP(A802,BD!$A$2:$E$3988,4,0) -> SIRENA - 2 mm - 18 mm - 191 mm | E802: =+VLOOKUP(A802,BD!$A$2:$E$3988,5,0) -> 4244.4 | G802: =IF($G$7="SI",ROUND(E802-(E802*DES.1),2)*1.21,ROUND(E802-(E802*DES.1),2)) -> 2291.98 | I802: {=+ROUND(G802+(G802*DES.2),2)} -> 4125.56 | O802: =+IFERROR(VLOOKUP(A802,Imagen!A:B,2,0),"")
A803: RESORTES LINEA HORNO205 | C803: =+VLOOKUP(A803,BD!$A$2:$E$3988,3,0) -> 205 | D803: =+VLOOKUP(A803,BD!$A$2:$E$3988,4,0) -> ORBIS COQUETA - 1,75 mm - 15 mm - 167 mm | E803: =+VLOOKUP(A803,BD!$A$2:$E$3988,5,0) -> 4011.48 | G803: =IF($G$7="SI",ROUND(E803-(E803*DES.1),2)*1.21,ROUND(E803-(E803*DES.1),2)) -> 2166.2 | I803: {=+ROUND(G803+(G803*DES.2),2)} -> 3899.16 | O803: =+IFERROR(VLOOKUP(A803,Imagen!A:B,2,0),"")
A804: RESORTES LINEA HORNO208 | C804: =+VLOOKUP(A804,BD!$A$2:$E$3988,3,0) -> 208 | D804: =+VLOOKUP(A804,BD!$A$2:$E$3988,4,0) -> ORBIS GALA - 1,75 mm - 15 mm - 205 mm | E804: =+VLOOKUP(A804,BD!$A$2:$E$3988,5,0) -> 4244.4 | G804: =IF($G$7="SI",ROUND(E804-(E804*DES.1),2)*1.21,ROUND(E804-(E804*DES.1),2)) -> 2291.98 | I804: {=+ROUND(G804+(G804*DES.2),2)} -> 4125.56 | O804: =+IFERROR(VLOOKUP(A804,Imagen!A:B,2,0),"")
A805: RESORTES LINEA HORNO210 | C805: =+VLOOKUP(A805,BD!$A$2:$E$3988,3,0) -> 210 | D805: =+VLOOKUP(A805,BD!$A$2:$E$3988,4,0) -> ORO AZUL GALAXIA - 1,5 mm - 13,3 mm - 172 mm | E805: =+VLOOKUP(A805,BD!$A$2:$E$3988,5,0) -> 4083.56 | G805: =IF($G$7="SI",ROUND(E805-(E805*DES.1),2)*1.21,ROUND(E805-(E805*DES.1),2)) -> 2205.12 | I805: {=+ROUND(G805+(G805*DES.2),2)} -> 3969.22 | O805: =+IFERROR(VLOOKUP(A805,Imagen!A:B,2,0),"")
A806: RESORTES LINEA HORNO211 | C806: =+VLOOKUP(A806,BD!$A$2:$E$3988,3,0) -> 211 | D806: =+VLOOKUP(A806,BD!$A$2:$E$3988,4,0) -> ORO AZUL ULTIMO MODELO - 1,5 mm - 10,5 mm - 185 mm | E806: =+VLOOKUP(A806,BD!$A$2:$E$3988,5,0) -> 4011.48 | G806: =IF($G$7="SI",ROUND(E806-(E806*DES.1),2)*1.21,ROUND(E806-(E806*DES.1),2)) -> 2166.2 | I806: {=+ROUND(G806+(G806*DES.2),2)} -> 3899.16 | O806: =+IFERROR(VLOOKUP(A806,Imagen!A:B,2,0),"")
A807: RESORTES LINEA HORNO214 | C807: =+VLOOKUP(A807,BD!$A$2:$E$3988,3,0) -> 214 | D807: =+VLOOKUP(A807,BD!$A$2:$E$3988,4,0) -> ARTHUR MARTHIN - 1,5 mm - 10,5 mm - 333,5 mm | E807: =+VLOOKUP(A807,BD!$A$2:$E$3988,5,0) -> 5372.04 | G807: =IF($G$7="SI",ROUND(E807-(E807*DES.1),2)*1.21,ROUND(E807-(E807*DES.1),2)) -> 2900.9 | I807: {=+ROUND(G807+(G807*DES.2),2)} -> 5221.62 | O807: =+IFERROR(VLOOKUP(A807,Imagen!A:B,2,0),"")
...

Sheet NUESTROS COMBOS
B1: NUESTROS SURTIDOS | G1: OPCION REDUCIDA | K1: PERSONALIZÁ TU COMBO | L1: *Todos los Surtidos incluyen el exhibidor + las gavetas y un stock inicial de toda la mercadería
B2: Codigo | C2: SURTIDO | D2: Importe P. Lista Cant. Estándar | E2: Importe Final c/descuento | F2: Cantidades Estándar | G2: Surtido Reducido | H2: Importe Final c/descuento | I2: Cant. Reducido | J2: Total Piezas | K2: ENLACE WEB
B3: PL CH. | C3: Plasticos Chico | D3: 865717.51 | E3: =+'NUESTROS COMBOS'!$D3-('NUESTROS COMBOS'!$D3*$M$4) -> 467487.46 | F3: 11 | G3: 281050.23 | H3: =+Table_1[[#This Row],[Surtido Reducido]]-(Table_1[[#This Row],[Surtido Reducido]]*$M$4) -> 151767.12 | I3: 3 | J3: 274 | K3: =+HYPERLINK(Q3,"IR - Comprar y/o Personalizar") -> IR - Comprar y/o Personalizar | M3: Descuento: | Q3: https://www.fabricamaxifer.com/plasticos-chico.html
B4: PL INT 1 | C4: Plasticos Int.1 | D4: 1148270.3 | E4: =+'NUESTROS COMBOS'!$D4-('NUESTROS COMBOS'!$D4*$M$4) -> 620065.97 | F4: 6 - 4 | G4: 653398.2 | H4: =+Table_1[[#This Row],[Surtido Reducido]]-(Table_1[[#This Row],[Surtido Reducido]]*$M$4) -> 352835.03 | I4: 3 | J4: 544 | K4: =+HYPERLINK(Q4,"IR - Comprar y/o Personalizar") -> IR - Comprar y/o Personalizar | M4: =+DES.1 -> 0.46 | Q4: https://www.fabricamaxifer.com/plasticos-int-1.html
B5: PL INT 2 | C5: Plasticos Int.2 | D5: 1294240.9 | E5: =+'NUESTROS COMBOS'!$D5-('NUESTROS COMBOS'!$D5*$M$4) -> 698890.1 | F5: 6 - 4 | G5: 739777.44 | H5: =+Table_1[[#This Row],[Surtido Reducido]]-(Table_1[[#This Row],[Surtido Reducido]]*$M$4) -> 399479.82 | I5: 3 | J5: 526 | K5: =+HYPERLINK(Q5,"IR - Comprar y/o Personalizar") -> IR - Comprar y/o Personalizar | Q5: https://www.fabricamaxifer.com/plasticos-int-2.html
B6: PL COMP. | C6: Plasticos Completo | D6: 2412511.2 | E6: =+'NUESTROS COMBOS'!$D6-('NUESTROS COMBOS'!$D6*$M$4) -> 1302756.1 | F6: 6 - 4 | G6: 1363175.6 | H6: =+Table_1[[#This Row],[Surtido Reducido]]-(Table_1[[#This Row],[Surtido Reducido]]*$M$4) -> 736114.85 | I6: 3 | J6: 1069 | K6: =+HYPERLINK(Q6,"IR - Comprar y/o Personalizar") -> IR - Comprar y/o Personalizar | Q6: https://www.fabricamaxifer.com/plasticos-completo.html
B7: CL. IMP 1 | C7: Clips Importados 1 | D7: 833999.68 | E7: =+'NUESTROS COMBOS'!$D7-('NUESTROS COMBOS'!$D7*$M$4) -> 450359.83 | F7: 4 | G7: 651749.76 | H7: =+Table_1[[#This Row],[Surtido Reducido]]-(Table_1[[#This Row],[Surtido Reducido]]*$M$4) -> 351944.87 | I7: 3 | J7: 486 | K7: =+HYPERLINK(Q7,"IR - Comprar y/o Personalizar") -> IR - Comprar y/o Personalizar | Q7: https://www.fabricamaxifer.com/clips-importados-1.html
B8: CL. IMP 2 | C8: Clips Importados 2 | D8: 846520.84 | E8: =+'NUESTROS COMBOS'!$D8-('NUESTROS COMBOS'!$D8*$M$4) -> 457121.25 | F8: 4 | G8: 661140.63 | H8: =+Table_1[[#This Row],[Surtido Reducido]]-(Table_1[[#This Row],[Surtido Reducido]]*$M$4) -> 357015.94 | I8: 3 | J8: 492 | K8: =+HYPERLINK(Q8,"IR - Comprar y/o Personalizar") -> IR - Comprar y/o Personalizar | Q8: https://www.fabricamaxifer.com/clips-importados-2.html
B9: CL. IMP COM | C9: Clips Importados Completo | D9: 1680520.5 | E9: =+'NUESTROS COMBOS'!$D9-('NUESTROS COMBOS'!$D9*$M$4) -> 907481.08 | F9: 4 | G9: 1312890.4 | H9: =+Table_1[[#This Row],[Surtido Reducido]]-(Table_1[[#This Row],[Surtido Reducido]]*$M$4) -> 708960.81 | I9: 3 | J9: 978 | K9: =+HYPERLINK(Q9,"IR - Comprar y/o Personalizar") -> IR - Comprar y/o Personalizar | Q9: https://www.fabricamaxifer.com/clips-importados-completo.html
B10: RES. LF | C10: Resortes Lf | D10: 681190.56 | E10: =+'NUESTROS COMBOS'!$D10-('NUESTROS COMBOS'!$D10*$M$4) -> 367842.9 | F10: 4 | G10: 385595.28 | H10: =+Table_1[[#This Row],[Surtido Reducido]]-(Table_1[[#This Row],[Surtido Reducido]]*$M$4) -> 208221.45 | I10: 2 | J10: 179 | K10: =+HYPERLINK(Q10,"IR - Comprar y/o Personalizar") -> IR - Comprar y/o Personalizar | Q10: https://www.fabricamaxifer.com/resortes-lf.html
B11: RES. LA | C11: Resortes La | D11: 371796 | E11: =+'NUESTROS COMBOS'!$D11-('NUESTROS COMBOS'!$D11*$M$4) -> 200769.84 | F11: 3 | G11: 268464 | H11: =+Table_1[[#This Row],[Surtido Reducido]]-(Table_1[[#This Row],[Surtido Reducido]]*$M$4) -> 144970.56 | I11: 2 | J11: 104 | K11: =+HYPERLINK(Q11,"IR - Comprar y/o Personalizar") -> IR - Comprar y/o Personalizar | Q11: https://www.fabricamaxifer.com/resortes-la.html
B12: RES. LC | C12: Resortes Lc | D12: 689359.04 | E12: =+'NUESTROS COMBOS'!$D12-('NUESTROS COMBOS'!$D12*$M$4) -> 372253.88 | F12: 4 | G12: 389679.52 | H12: =+Table_1[[#This Row],[Surtido Reducido]]-(Table_1[[#This Row],[Surtido Reducido]]*$M$4) -> 210426.94 | I12: 2 | J12: 223 | K12: =+HYPERLINK(Q12,"IR - Comprar y/o Personalizar") -> IR - Comprar y/o Personalizar | Q12: https://www.fabricamaxifer.com/resortes-lc.html
B13: RES. LP | C13: Resortes Lp | D13: 817647 | E13: =+'NUESTROS COMBOS'!$D13-('NUESTROS COMBOS'!$D13*$M$4) -> 441529.38 | F13: 3 | G13: 570098 | H13: =+Table_1[[#This Row],[Surtido Reducido]]-(Table_1[[#This Row],[Surtido Reducido]]*$M$4) -> 307852.92 | I13: 2 | J13: 80 | K13: =+HYPERLINK(Q13,"IR - Comprar y/o Personalizar") -> IR - Comprar y/o Personalizar | Q13: https://www.fabricamaxifer.com/resortes-lp.html
B14: RES. LB | C14: Resortes Lb | D14: 564024.96 | E14: =+'NUESTROS COMBOS'!$D14-('NUESTROS COMBOS'!$D14*$M$4) -> 304573.48 | F14: 3 | G14: 406016.64 | H14: =+Table_1[[#This Row],[Surtido Reducido]]-(Table_1[[#This Row],[Surtido Reducido]]*$M$4) -> 219248.99 | I14: 2 | J14: 77 | K14: =+HYPERLINK(Q14,"IR - Comprar y/o Personalizar") -> IR - Comprar y/o Personalizar | Q14: https://www.fabricamaxifer.com/resortes-lb.html
B15: GA+CH COMP. | C15: Ganchos - Chavetas / Completo | D15: 424440.67 | E15: =+'NUESTROS COMBOS'!$D15-('NUESTROS COMBOS'!$D15*$M$4) -> 229197.96 | F15: 3 - 5 - 2 | G15: 320223.41 | H15: =+Table_1[[#This Row],[Surtido Reducido]]-(Table_1[[#This Row],[Surtido Reducido]]*$M$4) -> 172920.64 | I15: 3 | J15: 126 | K15: =+HYPERLINK(Q15,"IR - Comprar y/o Personalizar") -> IR - Comprar y/o Personalizar | Q15: https://www.fabricamaxifer.com/ganchos-chavetas-completo.html
B16: GAN. + CHA. | C16: Ganchos - Chavetas | D16: 233471.52 | E16: =+'NUESTROS COMBOS'!$D16-('NUESTROS COMBOS'!$D16*$M$4) -> 126074.62 | F16: 4 - 6 - 10 - 3 | G16: 165732.72 | H16: =+Table_1[[#This Row],[Surtido Reducido]]-(Table_1[[#This Row],[Surtido Reducido]]*$M$4) -> 89495.669 | I16: 3 | J16: 75 | K16: =+HYPERLINK(Q16,"IR - Comprar y/o Personalizar") -> IR - Comprar y/o Personalizar | Q16: https://www.fabricamaxifer.com/ganchos-chavetas.html
... B71: TR Espec. + Torn. | C71: Tornillos Especiales + Tr Completo | D71: 816791.5 | E71: =+'NUESTROS COMBOS'!$D71-('NUESTROS COMBOS'!$D71*$M$4) -> 441067.41 | F71: 5 | G71: 528074.9 | H71: =+Table_1[[#This Row],[Surtido Reducido]]-(Table_1[[#This Row],[Surtido Reducido]]*$M$4) -> 285160.45 | I71: 3 | J71: 402 | K71: =+HYPERLINK(Q71,"IR - Comprar y/o Personalizar") -> IR - Comprar y/o Personalizar | Q71: https://www.fabricamaxifer.com/tornillos-especiales-y-tuercas-rapidas-completo.html
B73: * Los precios no incluyen IVA ** 1 pieza va en el exhibidor

Sheet BD
A1: ID | B1: Producto | C1: Numero | D1: Descripción | E1: Precio | F1: Codigo | H1: Orden Productos
A2: =+Table_2[[#This Row],[Producto]]&Table_2[[#This Row],[Numero]] -> PLASTICOS1 | B2: PLASTICOS | C2: 1 | D2: Grampa tapizado R11- R18 | E2: =+VLOOKUP(Table_2[[#This Row],[ID]],LISTAS[],3,0) -> 1159.02 | F2: 039.039.0003 | G2: 1 | H2: PLASTICOS
A3: =+Table_2[[#This Row],[Producto]]&Table_2[[#This Row],[Numero]] -> PLASTICOS2 | B3: PLASTICOS | C3: 2 | D3: Grampa tapizadoDuna-128-147 | E3: =+VLOOKUP(Table_2[[#This Row],[ID]],LISTAS[],3,0) -> 578.93 | F3: 039.039.0004 | G3: =+G2+1 -> 2 | H3: RESORTES LINEA FERRETERIA
A4: =+Table_2[[#This Row],[Producto]]&Table_2[[#This Row],[Numero]] -> PLASTICOS3 | B4: PLASTICOS | C4: 3 | D4: Tuerca autorros. FIAT-RENAULT | E4: =+VLOOKUP(Table_2[[#This Row],[ID]],LISTAS[],3,0) -> 629.53 | F4: 039.039.0005 | G4: =+G3+1 -> 3 | H4: RESORTES LINEA COMPLEMENTARIA
A5: =+Table_2[[#This Row],[Producto]]&Table_2[[#This Row],[Numero]] -> PLASTICOS4 | B5: PLASTICOS | C5: 4 | D5: Fijacion consola GACELL | E5: =+VLOOKUP(Table_2[[#This Row],[ID]],LISTAS[],3,0) -> 654.85 | F5: 039.039.0006 | G5: =+G4+1 -> 4 | H5: RESORTES LINEA PESADA
A6: =+Table_2[[#This Row],[Producto]]&Table_2[[#This Row],[Numero]] -> PLASTICOS5 | B6: PLASTICOS | C6: 5 | D6: Fijacion OPTICA 128 | E6: =+VLOOKUP(Table_2[[#This Row],[ID]],LISTAS[],3,0) -> 727.61 | F6: 039.039.0007 | G6: =+G5+1 -> 5 | H6: RESORTES LINEA BULONERA
A7: =+Table_2[[#This Row],[Producto]]&Table_2[[#This Row],[Numero]] -> PLASTICOS6 | B7: PLASTICOS | C7: 6 | D7: Tuerca autorros. GACELL | E7: =+VLOOKUP(Table_2[[#This Row],[ID]],LISTAS[],3,0) -> 914.71 | F7: 039.039.0008 | G7: =+G6+1 -> 6 | H7: RESORTES LINEA AUTOMOTOR
A8: =+Table_2[[#This Row],[Producto]]&Table_2[[#This Row],[Numero]] -> PLASTICOS7 | B8: PLASTICOS | C8: 7 | D8: Fijacion patente FIAT | E8: =+VLOOKUP(Table_2[[#This Row],[ID]],LISTAS[],3,0) -> 578.93 | F8: 039.039.0009 | G8: =+G7+1 -> 7 | H8: RESORTES LINEA HORNO
A9: =+Table_2[[#This Row],[Producto]]&Table_2[[#This Row],[Numero]] -> PLASTICOS8 | B9: PLASTICOS | C9: 8 | D9: Registro faro 125 | E9: =+VLOOKUP(Table_2[[#This Row],[ID]],LISTAS[],3,0) -> 654.85 | F9: 039.039.0010 | G9: =+G8+1 -> 8 | H9: ORING
A10: =+Table_2[[#This Row],[Producto]]&Table_2[[#This Row],[Numero]] -> PLASTICOS9 | B10: PLASTICOS | C10: 9 | D10: Tuerca autorroscante FIAT | E10: =+VLOOKUP(Table_2[[#This Row],[ID]],LISTAS[],3,0) -> 680.9 | F10: 039.039.0011 | G10: =+G9+1 -> 9 | H10: CARBONES
A11: =+Table_2[[#This Row],[Producto]]&Table_2[[#This Row],[Numero]] -> PLASTICOS10 | B11: PLASTICOS | C11: 10 | D11: Fijacion capot 125 | E11: =+VLOOKUP(Table_2[[#This Row],[ID]],LISTAS[],3,0) -> 771.26 | F11: 039.039.0012 | G11: =+G10+1 -> 10 | H11: TERMINALES
A12: =+Table_2[[#This Row],[Producto]]&Table_2[[#This Row],[Numero]] -> PLASTICOS11 | B12: PLASTICOS | C12: 11 | D12: Tuerca parrilla DUNA- UNO | E12: =+VLOOKUP(Table_2[[#This Row],[ID]],LISTAS[],3,0) -> 917.77 | F12: 039.039.0013 | G12: =+G11+1 -> 11 | H12: REGATONES
A13: =+Table_2[[#This Row],[Producto]]&Table_2[[#This Row],[Numero]] -> PLASTICOS12 | B13: PLASTICOS | C13: 12 | D13: Tuerca autorroc. PEUGEOT | E13: =+VLOOKUP(Table_2[[#This Row],[ID]],LISTAS[],3,0) -> 933.24 | F13: 039.039.0014 | G13: =+G12+1 -> 12 | H13: ARANDELAS DE GOMA
A14: =+Table_2[[#This Row],[Producto]]&Table_2[[#This Row],[Numero]] -> PLASTICOS13 | B14: PLASTICOS | C14: 13 | D14: Tuerca autorros. FIAT-PEUGEOT | E14: =+VLOOKUP(Table_2[[#This Row],[ID]],LISTAS[],3,0) -> 1202.08 | F14: 039.039.0015 | G14: =+G13+1 -> 13 | H14: ARANDELAS DE GOMA LINEA PESADA
... A56: =+Table_2[[#This Row],[Producto]]&Table_2[[#This Row],[Numero]] -> PLASTICOS55 | B56: PLASTICOS | C56: 55 | D56: Grampa varilla cerradura FIAT DUNA UNO | E56: =+VLOOKUP(Table_2[[#This Row],[ID]],LISTAS[],3,0) -> 778.17 | F56: 039.039.0057 | G56: =+G55+1 -> 55 | H56: TUERCAS RAPIDAS NUEVAS
A57: =+Table_2[[#This Row],[Producto]]&Table_2[[#This Row],[Numero]] -> PLASTICOS56 | B57: PLASTICOS | C57: 56 | D57: Buje insignia FIAT UNO-DUNA | E57: =+VLOOKUP(Table_2[[#This Row],[ID]],LISTAS[],3,0) -> 578.93 | F57: 039.039.0058 | G57: 56 | H57: CONECTORES DE COMBUSTIBLE
A58: =+Table_2[[#This Row],[Producto]]&Table_2[[#This Row],[Numero]] -> PLASTICOS57 | B58: PLASTICOS | C58: 57 | D58: Tuerca apoya brazo VOLKSWEGEN GACELL | E58: =+VLOOKUP(Table_2[[#This Row],[ID]],LISTAS[],3,0) -> 1845.05 | F58: 039.039.0059
A59: =+Table_2[[#This Row],[Producto]]&Table_2[[#This Row],[Numero]] -> PLASTICOS58 | B59: PLASTICOS | C59: 58 | D59: Grampa bagueta zocalo R11 | E59: =+VLOOKUP(Table_2[[#This Row],[ID]],LISTAS[],3,0) -> 1088.84 | F59: 039.039.0060
A60: =+Table_2[[#This Row],[Producto]]&Table_2[[#This Row],[Numero]] -> PLASTICOS59 | B60: PLASTICOS | C60: 59 | D60: Grampa bagueta zocalo R11 | E60: =+VLOOKUP(Table_2[[#This Row],[ID]],LISTAS[],3,0) -> 964.7 | F60: 039.039.0061
A61: =+Table_2[[#This Row],[Producto]]&Table_2[[#This Row],[Numero]] -> PLASTICOS60 | B61: PLASTICOS | C61: 60 | D61: Grampa bagueta zocalo R11 roja | E61: =+VLOOKUP(Table_2[[#This Row],[ID]],LISTAS[],3,0) -> 964.7 | F61: 039.039.0062
A62: =+Table_2[[#This Row],[Producto]]&Table_2[[#This Row],[Numero]] -> PLASTICOS61 | B62: PLASTICOS | C62: 61 | D62: grampa varilla cerradura FIAT 600 - PEUGEOT | E62: =+VLOOKUP(Table_2[[#This Row],[ID]],LISTAS[],3,0) -> 910.22 | F62: 039.039.0063
A63: =+Table_2[[#This Row],[Producto]]&Table_2[[#This Row],[Numero]] -> PLASTICOS62 | B63: PLASTICOS | C63: 62 | D63: Grampa tapizado Renault 21 | E63: =+VLOOKUP(Table_2[[#This Row],[ID]],LISTAS[],3,0) -> 1027.04 | F63: 039.039.0064
A64: =+Table_2[[#This Row],[Producto]]&Table_2[[#This Row],[Numero]] -> PLASTICOS63 | B64: PLASTICOS | C64: 63 | D64: Grampa paragolpe Ford Ka | E64: =+VLOOKUP(Table_2[[#This Row],[ID]],LISTAS[],3,0) -> 1244.49 | F64: 039.039.0065
A65: =+Table_2[[#This Row],[Producto]]&Table_2[[#This Row],[Numero]] -> PLASTICOS64 | B65: PLASTICOS | C65: 64 | D65: Grampa tapizado Renault 19 | E65: =+VLOOKUP(Table_2[[#This Row],[ID]],LISTAS[],3,0) -> 1186.46 | F65: 039.039.0066
A66: =+Table_2[[#This Row],[Producto]]&Table_2[[#This Row],[Numero]] -> PLASTICOS65 | B66: PLASTICOS | C66: 65 | D66: Grampa tapizado Peugeot 405 larga | E66: =+VLOOKUP(Table_2[[#This Row],[ID]],LISTAS[],3,0) -> 1027.04 | F66: 039.039.0067
A67: =+Table_2[[#This Row],[Producto]]&Table_2[[#This Row],[Numero]] -> PLASTICOS66 | B67: PLASTICOS | C67: 66 | D67: Grampa tapizado puerta Chevr. Corsa | E67: =+VLOOKUP(Table_2[[#This Row],[ID]],LISTAS[],3,0) -> 756.71 | F67: 039.039.0068
A68: =+Table_2[[#This Row],[Producto]]&Table_2[[#This Row],[Numero]] -> PLASTICOS67 | B68: PLASTICOS | C68: 67 | D68: Grampa tapizado Ford Ka | E68: =+VLOOKUP(Table_2[[#This Row],[ID]],LISTAS[],3,0) -> 1244.49 | F68: 039.039.0069
A69: =+Table_2[[#This Row],[Producto]]&Table_2[[#This Row],[Numero]] -> PLASTICOS69 | B69: PLASTICOS | C69: 69 | D69: Grampa pasacable omega grande | E69: =+VLOOKUP(Table_2[[#This Row],[ID]],LISTAS[],3,0) -> 683.78 | F69: 039.039.0070
... A1084: =+Table_2[[#This Row],[Producto]]&Table_2[[#This Row],[Numero]] -> ORING402 | B1084: ORING | C1084: 402 | D1084: Cuerda 5,30mm - Nitrilo | E1084: =+VLOOKUP(Table_2[[#This Row],[ID]],LISTAS[],3,0) -> 4474.8 | F1084: 036.036.0151
A1085: =+Table_2[[#This Row],[Producto]]&Table_2[[#This Row],[Numero]] -> INSERTOS4X6 | B1085: INSERTOS | C1085: 4X6 | D1085: 4X6 | E1085: =+VLOOKUP(Table_2[[#This Row],[ID]],LISTAS[],3,0) -> 1861.56 | F1085: 031.031.0003
A1086: =+Table_2[[#This Row],[Producto]]&Table_2[[#This Row],[Numero]] -> INSERTOS5X7 | B1086: INSERTOS | C1086: 5X7 | D1086: 5X7 | E1086: =+VLOOKUP(Table_2[[#This Row],[ID]],LISTAS[],3,0) -> 1861.56 | F1086: 031.031.0004
A1087: =+Table_2[[#This Row],[Producto]]&Table_2[[#This Row],[Numero]] -> INSERTOS6X8 | B1087: INSERTOS | C1087: 6X8 | D1087: 6X8 | E1087: =+VLOOKUP(Table_2[[#This Row],[ID]],LISTAS[],3,0) -> 1861.56 | F1087: 031.031.0005
A1088: =+Table_2[[#This Row],[Producto]]&Table_2[[#This Row],[Numero]] -> INSERTOS7X10 | B1088: INSERTOS | C1088: 7X10 | D1088: 7X10 | E1088: =+VLOOKUP(Table_2[[#This Row],[ID]],LISTAS[],3,0) -> 1861.56 | F1088: 031.031.0006
A1089: =+Table_2[[#This Row],[Producto]]&Table_2[[#This Row],[Numero]] -> INSERTOS8X1X11 | B1089: INSERTOS | C1089: 8X1X11 | D1089: 8X1X11 | E1089: =+VLOOKUP(Table_2[[#This Row],[ID]],LISTAS[],3,0) -> 1861.56 | F1089: 031.031.0007
A1090: =+Table_2[[#This Row],[Producto]]&Table_2[[#This Row],[Numero]] -> INSERTOS8X11 | B1090: INSERTOS | C1090: 8X11 | D1090: 8X11 | E1090: =+VLOOKUP(Table_2[[#This Row],[ID]],LISTAS[],3,0) -> 1861.56 | F1090: 031.031.0008
A1091: =+Table_2[[#This Row],[Producto]]&Table_2[[#This Row],[Numero]] -> INSERTOS9X12 | B1091: INSERTOS | C1091: 9X12 | D1091: 9X12 | E1091: =+VLOOKUP(Table_2[[#This Row],[ID]],LISTAS[],3,0) -> 1861.56 | F1091: 031.031.0009
A1092: =+Table_2[[#This Row],[Producto]]&Table_2[[#This Row],[Numero]] -> INSERTOS10X1X1/2 | B1092: INSERTOS | C1092: 10X1X1/2 | D1092: 10X1X1/2 | E1092: =+VLOOKUP(Table_2[[#This Row],[ID]],LISTAS[],3,0) -> 1861.56 | F1092: 031.031.0010
A1093: =+Table_2[[#This Row],[Producto]]&Table_2[[#This Row],[Numero]] -> INSERTOS10X1,25X1/2 | B1093: INSERTOS | C1093: 10X1,25X1/2 | D1093: 10X1,25X1/2 | E1093: =+VLOOKUP(Table_2[[#This Row],[ID]],LISTAS[],3,0) -> 1861.56 | F1093: 031.031.0011
A1094: =+Table_2[[#This Row],[Producto]]&Table_2[[#This Row],[Numero]] -> INSERTOS10x1,5x1/2 | B1094: INSERTOS | C1094: 10x1,5x1/2 | D1094: 10x1,5x1/2 | E1094: =+VLOOKUP(Table_2[[#This Row],[ID]],LISTAS[],3,0) -> 1861.56 | F1094: 031.031.0012
A1095: =+Table_2[[#This Row],[Producto]]&Table_2[[#This Row],[Numero]] -> INSERTOS11x14 | B1095: INSERTOS | C1095: 11x14 | D1095: 11x14 | E1095: =+VLOOKUP(Table_2[[#This Row],[ID]],LISTAS[],3,0) -> 2349.2 | F1095: 031.031.0013
A1096: =+Table_2[[#This Row],[Producto]]&Table_2[[#This Row],[Numero]] -> INSERTOS12x1,25x16 | B1096: INSERTOS | C1096: 12x1,25x16 | D1096: 12x1,25x16 | E1096: =+VLOOKUP(Table_2[[#This Row],[ID]],LISTAS[],3,0) -> 2811.11 | F1096: 031.031.0014
... A1110: =+Table_2[[#This Row],[Producto]]&Table_2[[#This Row],[Numero]] -> INSERTOSArand. Tapa - 14x26 | B1110: INSERTOS | C1110: Arand. Tapa - 14x26 | D1110: Arand. Tapa - 14x26 | E1110: =+VLOOKUP(Table_2[[#This Row],[ID]],LISTAS[],3,0) -> 1866.67 | F1110: 031.031.0028
A1111: =+Table_2[[#This Row],[Producto]]&Table_2[[#This Row],[Numero]] -> CONEXIÓN DE CHAPA1 | B1111: CONEXIÓN DE CHAPA | C1111: 1 | D1111: Conector de 3 vías G.N.C. de 16 m x 16 mm | E1111: =+VLOOKUP(Table_2[[#This Row],[ID]],LISTAS[],3,0) -> 0 | F1111: 026.026.0003
A1112: =+Table_2[[#This Row],[Producto]]&Table_2[[#This Row],[Numero]] -> CONEXIÓN DE CHAPA2 | B1112: CONEXIÓN DE CHAPA | C1112: 2 | D1112: Conector de 3 vías G.N.C. de 16 m x 8 mm | E1112: =+VLOOKUP(Table_2[[#This Row],[ID]],LISTAS[],3,0) -> 0 | F1112: 026.026.0004
A1113: =+Table_2[[#This Row],[Producto]]&Table_2[[#This Row],[Numero]] -> CONEXIÓN DE CHAPA3 | B1113: CONEXIÓN DE CHAPA | C1113: 3 | D1113: conector de 3 vias de 13 mm x 13 mm | E1113: =+VLOOKUP(Table_2[[#This Row],[ID]],LISTAS[],3,0) -> 0 | F1113: 026.026.0005
A1114: =+Table_2[[#This Row],[Producto]]&Table_2[[#This Row],[Numero]] -> CONEXIÓN DE CHAPA4 | B1114: CONEXIÓN DE CHAPA | C1114: 4 | D1114: Conector de 3 vías G.N.C. de 19 m x 8 mm | E1114: =+VLOOKUP(Table_2[[#This Row],[ID]],LISTAS[],3,0) -> 0 | F1114: 026.026.0006
A1115: =+Table_2[[#This Row],[Producto]]&Table_2[[#This Row],[Numero]] -> CONEXIÓN DE CHAPA5 | B1115: CONEXIÓN DE CHAPA | C1115: 5 | D1115: conector de 3 vias de 35 mm x 19 mm | E1115: =+VLOOKUP(Table_2[[#This Row],[ID]],LISTAS[],3,0) -> 0 | F1115: 026.026.0007
A1116: =+Table_2[[#This Row],[Producto]]&Table_2[[#This Row],[Numero]] -> CONEXIÓN DE CHAPA7 | B1116: CONEXIÓN DE CHAPA | C1116: 7 | D1116: conector de 3 vias de 19 mm x 16 mm | E1116: =+VLOOKUP(Table_2[[#This Row],[ID]],LISTAS[],3,0) -> 0 | F1116: 026.026.0008
A1117: =+Table_2[[#This Row],[Producto]]&Table_2[[#This Row],[Numero]] -> CONEXIÓN DE CHAPA8 | B1117: CONEXIÓN DE CHAPA | C1117: 8 | D1117: conector de 3 vias de 19 mm x 13 mm | E1117: =+VLOOKUP(Table_2[[#This Row],[ID]],LISTAS[],3,0) -> 0 | F1117: 026.026.0009
A1118: =+Table_2[[#This Row],[Producto]]&Table_2[[#This Row],[Numero]] -> CONEXIÓN DE CHAPA9 | B1118: CONEXIÓN DE CHAPA | C1118: 9 | D1118: conector de 3 vias de 19 mm x 19 mm | E1118: =+VLOOKUP(Table_2[[#This Row],[ID]],LISTAS[],3,0) -> 0 | F1118: 026.026.0010
A1119: =+Table_2[[#This Row],[Producto]]&Table_2[[#This Row],[Numero]] -> CONEXIÓN DE CHAPA12 | B1119: CONEXIÓN DE CHAPA | C1119: 12 | D1119: conector recto con porta bulbo de 25 mm x 120 mm | E1119: =+VLOOKUP(Table_2[[#This Row],[ID]],LISTAS[],3,0) -> 0 | F1119: 026.026.0011
A1120: =+Table_2[[#This Row],[Producto]]&Table_2[[#This Row],[Numero]] -> CONEXIÓN DE CHAPA13 | B1120: CONEXIÓN DE CHAPA | C1120: 13 | D1120: conector recto con porta bulbo de 29 mm x 120 mm | E1120: =+VLOOKUP(Table_2[[#This Row],[ID]],LISTAS[],3,0) -> 0 | F1120: 026.026.0012
A1121: =+Table_2[[#This Row],[Producto]]&Table_2[[#This Row],[Numero]] -> CONEXIÓN DE CHAPA14 | B1121: CONEXIÓN DE CHAPA | C1121: 14 | D1121: conector recto con porta bulbo de 32 mm x 120 mm | E1121: =+VLOOKUP(Table_2[[#This Row],[ID]],LISTAS[],3,0) -> 0 | F1121: 026.026.0013
A1122: =+Table_2[[#This Row],[Producto]]&Table_2[[#This Row],[Numero]] -> CONEXIÓN DE CHAPA15 | B1122: CONEXIÓN DE CHAPA | C1122: 15 | D1122: conector recto con porta bulbo de 35 mm x 120 mm | E1122: =+VLOOKUP(Table_2[[#This Row],[ID]],LISTAS[],3,0) -> 0 | F1122: 026.026.0014
... A1296: =+Table_2[[#This Row],[Producto]]&Table_2[[#This Row],[Numero]] -> TUERCAS RAPIDAS8 | B1296: TUERCAS RAPIDAS | C1296: 8 | D1296: Embutida Larga - R 1/4 - 15 mm - 32 mm | E1296: =+VLOOKUP(Table_2[[#This Row],[ID]],LISTAS[],3,0) -> 1055 | F1296: 063.063.0008
A1297: =+Table_2[[#This Row],[Producto]]&Table_2[[#This Row],[Numero]] -> TUERCAS RAPIDAS9 CH | B1297: TUERCAS RAPIDAS | C1297: 9 CH | D1297: Reten embutida chica - 5 mm - 11 mm - 18 mm | E1297: =+VLOOKUP(Table_2[[#This Row],[ID]],LISTAS[],3,0) -> 660 | F1297: 063.063.0009
A1298: =+Table_2[[#This Row],[Producto]]&Table_2[[#This Row],[Numero]] -> TUERCAS RAPIDAS10 CH | B1298: TUERCAS RAPIDAS | C1298: 10 CH | D1298: Reten embutida chica - 6 mm - 11 mm - 18 mm | E1298: =+VLOOKUP(Table_2[[#This Row],[ID]],LISTAS[],3,0) -> 660 | F1298: 063.063.0010
A1299: =+Table_2[[#This Row],[Producto]]&Table_2[[#This Row],[Numero]] -> TUERCAS RAPIDAS9 | B1299: TUERCAS RAPIDAS | C1299: 9 | D1299: Reten embutida - 5 mm - 15 mm - 22 mm | E1299: =+VLOOKUP(Table_2[[#This Row],[ID]],LISTAS[],3,0) -> 860 | F1299: 063.063.0011
A1300: =+Table_2[[#This Row],[Producto]]&Table_2[[#This Row],[Numero]] -> TUERCAS RAPIDAS10 | B1300: TUERCAS RAPIDAS | C1300: 10 | D1300: Reten embutida - 6 mm - 15 mm - 22 mm | E1300: =+VLOOKUP(Table_2[[#This Row],[ID]],LISTAS[],3,0) -> 860 | F1300: 063.063.0012
A1301: =+Table_2[[#This Row],[Producto]]&Table_2[[#This Row],[Numero]] -> TUERCAS RAPIDAS12 | B1301: TUERCAS RAPIDAS | C1301: 12 | D1301: Tuerca cajon - 5 mm - 12 mm - 12 mm | E1301: =+VLOOKUP(Table_2[[#This Row],[ID]],LISTAS[],3,0) -> 925 | F1301: 063.063.0013
A1302: =+Table_2[[#This Row],[Producto]]&Table_2[[#This Row],[Numero]] -> TUERCAS RAPIDAS13 | B1302: TUERCAS RAPIDAS | C1302: 13 | D1302: Tuerca cajon - 6 mm - 12 mm - 12 mm | E1302: =+VLOOKUP(Table_2[[#This Row],[ID]],LISTAS[],3,0) -> 925 | F1302: 063.063.0014
A1303: =+Table_2[[#This Row],[Producto]]&Table_2[[#This Row],[Numero]] -> TUERCAS RAPIDAS14 | B1303: TUERCAS RAPIDAS | C1303: 14 | D1303: Reten parker - Park 4 - 8 mm - 12 mm | E1303: =+VLOOKUP(Table_2[[#This Row],[ID]],LISTAS[],3,0) -> 530 | F1303: 063.063.0015
A1304: =+Table_2[[#This Row],[Producto]]&Table_2[[#This Row],[Numero]] -> TUERCAS RAPIDAS15 | B1304: TUERCAS RAPIDAS | C1304: 15 | D1304: Reten parker - Park 6 - 12 mm - 19 mm | E1304: =+VLOOKUP(Table_2[[#This Row],[ID]],LISTAS[],3,0) -> 595 | F1304: 063.063.0016
A1305: =+Table_2[[#This Row],[Producto]]&Table_2[[#This Row],[Numero]] -> TUERCAS RAPIDAS16 | B1305: TUERCAS RAPIDAS | C1305: 16 | D1305: Reten parker - Park 6 - 12 mm - 16 mm | E1305: =+VLOOKUP(Table_2[[#This Row],[ID]],LISTAS[],3,0) -> 530 | F1305: 063.063.0017
A1306: =+Table_2[[#This Row],[Producto]]&Table_2[[#This Row],[Numero]] -> TUERCAS RAPIDAS17 | B1306: TUERCAS RAPIDAS | C1306: 17 | D1306: Reten parker - Park 8 - 12 mm - 19 mm | E1306: =+VLOOKUP(Table_2[[#This Row],[ID]],LISTAS[],3,0) -> 595 | F1306: 063.063.0018
A1307: =+Table_2[[#This Row],[Producto]]&Table_2[[#This Row],[Numero]] -> TUERCAS RAPIDAS18 | B1307: TUERCAS RAPIDAS | C1307: 18 | D1307: Reten parker - Park 7 - 11 mm - 17 mm | E1307: =+VLOOKUP(Table_2[[#This Row],[ID]],LISTAS[],3,0) -> 530 | F1307: 063.063.0019
A1308: =+Table_2[[#This Row],[Producto]]&Table_2[[#This Row],[Numero]] -> TUERCAS RAPIDAS19 | B1308: TUERCAS RAPIDAS | C1308: 19 | D1308: Reten parker - Park 8 - 11 mm - 24 mm | E1308: =+VLOOKUP(Table_2[[#This Row],[ID]],LISTAS[],3,0) -> 170 | F1308: 063.063.0020
A1309: =+Table_2[[#This Row],[Producto]]&Table_2[[#This Row],[Numero]] -> TUERCAS RAPIDAS20 | B1309: TUERCAS RAPIDAS | C1309: 20 | D1309: Reten parker cortada - Park 8 - 11 mm - 16 mm | E1309: =+VLOOKUP(Table_2[[#This Row],[ID]],LISTAS[],3,0) -> 160 | F1309: 063.063.0021
A1310: =+Table_2[[#This Row],[Producto]]&Table_2[[#This Row],[Numero]] -> TUERCAS RAPIDAS21 | B1310: TUERCAS RAPIDAS | C1310: 21 | D1310: Reten parker - Park 10 - 12 mm - 19 mm | E1310: =+VLOOKUP(Table_2[[#This Row],[ID]],LISTAS[],3,0) -> 595 | F1310: 063.063.0022
... A1315: =+Table_2[[#This Row],[Producto]]&Table_2[[#This Row],[Numero]] -> TUERCAS RAPIDAS28 | B1315: TUERCAS RAPIDAS | C1315: 28 | D1315: Reten parker - Park 12 - 14 mm - 21 mm | E1315: =+VLOOKUP(Table_2[[#This Row],[ID]],LISTAS[],3,0) -> 595 | F1315: 063.063.0027
A1316: =+Table_2[[#This Row],[Producto]]&Table_2[[#This Row],[Numero]] -> TUERCAS RAPIDAS32 | B1316: TUERCAS RAPIDAS | C1316: 32 | D1316: Aranlock 6x15 | E1316: =+VLOOKUP(Table_2[[#This Row],[ID]],LISTAS[],3,0) -> 295.96 | F1316: 063.063.0028 | H1316: *
A1317: =+Table_2[[#This Row],[Producto]]&Table_2[[#This Row],[Numero]] -> TUERCAS RAPIDAS33 | B1317: TUERCAS RAPIDAS | C1317: 33 | D1317: Aranlock 7x15 | E1317: =+VLOOKUP(Table_2[[#This Row],[ID]],LISTAS[],3,0) -> 295.96 | F1317: 063.063.0029
A1318: =+Table_2[[#This Row],[Producto]]&Table_2[[#This Row],[Numero]] -> TUERCAS RAPIDAS34 | B1318: TUERCAS RAPIDAS | C1318: 34 | D1318: Aranlock 8x16 | E1318: =+VLOOKUP(Table_2[[#This Row],[ID]],LISTAS[],3,0) -> 280.61 | F1318: 063.063.0030
A1319: =+Table_2[[#This Row],[Producto]]&Table_2[[#This Row],[Numero]] -> TUERCAS RAPIDAS35 | B1319: TUERCAS RAPIDAS | C1319: 35 | D1319: Aranlock 9x18 | E1319: =+VLOOKUP(Table_2[[#This Row],[ID]],LISTAS[],3,0) -> 155.9 | F1319: 063.063.0031
A1320: =+Table_2[[#This Row],[Producto]]&Table_2[[#This Row],[Numero]] -> TUERCAS RAPIDAS36 | B1320: TUERCAS RAPIDAS | C1320: 36 | D1320: Aranlock 10x18 | E1320: =+VLOOKUP(Table_2[[#This Row],[ID]],LISTAS[],3,0) -> 276.37 | F1320: 063.063.0032
A1321: =+Table_2[[#This Row],[Producto]]&Table_2[[#This Row],[Numero]] -> TUERCAS RAPIDAS42 | B1321: TUERCAS RAPIDAS | C1321: 42 | D1321: Tuerca inserto/madera - rosca de 3/16 | E1321: =+VLOOKUP(Table_2[[#This Row],[ID]],LISTAS[],3,0) -> 660 | F1321: 063.063.0033
A1322: =+Table_2[[#This Row],[Producto]]&Table_2[[#This Row],[Numero]] -> TUERCAS RAPIDAS43 | B1322: TUERCAS RAPIDAS | C1322: 43 | D1322: Tuerca inserto/madera - rosca de 5 mm | E1322: =+VLOOKUP(Table_2[[#This Row],[ID]],LISTAS[],3,0) -> 660 | F1322: 063.063.0034
A1323: =+Table_2[[#This Row],[Producto]]&Table_2[[#This Row],[Numero]] -> TUERCAS RAPIDAS44 | B1323: TUERCAS RAPIDAS | C1323: 44 | D1323: Tuerca inserto/madera - rosca de 1/4 | E1323: =+VLOOKUP(Table_2[[#This Row],[ID]],LISTAS[],3,0) -> 725 | F1323: 063.063.0035
A1324: =+Table_2[[#This Row],[Producto]]&Table_2[[#This Row],[Numero]] -> TUERCAS RAPIDAS45 | B1324: TUERCAS RAPIDAS | C1324: 45 | D1324: Tuerca inserto/madera - rosca de 6 mm | E1324: =+VLOOKUP(Table_2[[#This Row],[ID]],LISTAS[],3,0) -> 725 | F1324: 063.063.0036
A1325: =+Table_2[[#This Row],[Producto]]&Table_2[[#This Row],[Numero]] -> TUERCAS RAPIDAS46 | B1325: TUERCAS RAPIDAS | C1325: 46 | D1325: Tuerca inserto/madera - rosca de 5/16 mm | E1325: =+VLOOKUP(Table_2[[#This Row],[ID]],LISTAS[],3,0) -> 790 | F1325: 063.063.0037
A1326: =+Table_2[[#This Row],[Producto]]&Table_2[[#This Row],[Numero]] -> TUERCAS RAPIDAS47 | B1326: TUERCAS RAPIDAS | C1326: 47 | D1326: Tuerca inserto/madera - rosca de 8 mm | E1326: =+VLOOKUP(Table_2[[#This Row],[ID]],LISTAS[],3,0) -> 790 | F1326: 063.063.0038
A1327: =+Table_2[[#This Row],[Producto]]&Table_2[[#This Row],[Numero]] -> ARANDELAS DE COBRE7,5 x 15 x 1,5 | B1327: ARANDELAS DE COBRE | C1327: 7,5 x 15 x 1,5 | D1327: INYECTORES - CUMMING | E1327: =+VLOOKUP(Table_2[[#This Row],[ID]],LISTAS[],3,0) -> 1136 | F1327: 009.009.0003
A1328: =+Table_2[[#This Row],[Producto]]&Table_2[[#This Row],[Numero]] -> ARANDELAS DE COBRE7,5 x 15 x 2 | B1328: ARANDELAS DE COBRE | C1328: 7,5 x 15 x 2 | D1328: INYECTORES - CUMMING | E1328: =+VLOOKUP(Table_2[[#This Row],[ID]],LISTAS[],3,0) -> 1420.21 | F1328: 009.009.0004
A1329: =+Table_2[[#This Row],[Producto]]&Table_2[[#This Row],[Numero]] -> ARANDELAS DE COBRE7,5 x 15 x 3 | B1329: ARANDELAS DE COBRE | C1329: 7,5 x 15 x 3 | D1329: INYECTORES - | E1329: =+VLOOKUP(Table_2[[#This Row],[ID]],LISTAS[],3,0) -> 2366.09 | F1329: 009.009.0005
A1330: =+Table_2[[#This Row],[Producto]]&Table_2[[#This Row],[Numero]] -> ARANDELAS DE COBRE8 x 13 x 2,5 | B1330: ARANDELAS DE COBRE | C1330: 8 x 13 x 2,5 | D1330: INYECTORES - POLO | E1330: =+VLOOKUP(Table_2[[#This Row],[ID]],LISTAS[],3,0) -> 1578.18 | F1330: 009.009.0006
A1331: =+Table_2[[#This Row],[Producto]]&Table_2[[#This Row],[Numero]] -> ARANDELAS DE COBRE10 x 19 x 2 | B1331: ARANDELAS DE COBRE | C1331: 10 x 19 x 2 | D1331: INYECTORES - PERKINS Grande | E1331: =+VLOOKUP(Table_2[[#This Row],[ID]],LISTAS[],3,0) -> 1893.47 | F1331: 009.009.0007
A1332: =+Table_2[[#This Row],[Producto]]&Table_2[[#This Row],[Numero]] -> ARANDELAS DE COBRE10 x 20 x 1 | B1332: ARANDELAS DE COBRE | C1332: 10 x 20 x 1 | D1332: INYECTORES - M - Benz | E1332: =+VLOOKUP(Table_2[[#This Row],[ID]],LISTAS[],3,0) -> 1017.84 | F1332: 009.009.0008
A1333: =+Table_2[[#This Row],[Producto]]&Table_2[[#This Row],[Numero]] -> ARANDELAS DE COBRE14 x 20 x 1,5 | B1333: ARANDELAS DE COBRE | C1333: 14 x 20 x 1,5 | D1333: INYECTORES - PERKINS | E1333: =+VLOOKUP(Table_2[[#This Row],[ID]],LISTAS[],3,0) -> 1656.73 | F1333: 009.009.0009
A1334: =+Table_2[[#This Row],[Producto]]&Table_2[[#This Row],[Numero]] -> ARANDELAS DE COBRE14 x 20 x 2 | B1334: ARANDELAS DE COBRE | C1334: 14 x 20 x 2 | D1334: INYECTORES - INDENOR | E1334: =+VLOOKUP(Table_2[[#This Row],[ID]],LISTAS[],3,0) -> 1893.47 | F1334: 009.009.0010
A1335: =+Table_2[[#This Row],[Producto]]&Table_2[[#This Row],[Numero]] -> ARANDELAS DE COBRE14,5 x 21 x 2 | B1335: ARANDELAS DE COBRE | C1335: 14,5 x 21 x 2 | D1335: INYECTORES - R19 DIESEL | E1335: =+VLOOKUP(Table_2[[#This Row],[ID]],LISTAS[],3,0) -> 2130.42 | F1335: 009.009.0011
A1336: =+Table_2[[#This Row],[Producto]]&Table_2[[#This Row],[Numero]] -> ARANDELAS DE COBRE16 x 21 x 2 | B1336: ARANDELAS DE COBRE | C1336: 16 x 21 x 2 | D1336: INYECTORES - PEUGEOT 405 D | E1336: =+VLOOKUP(Table_2[[#This Row],[ID]],LISTAS[],3,0) -> 2130.42 | F1336: 009.009.0012
A1337: =+Table_2[[#This Row],[Producto]]&Table_2[[#This Row],[Numero]] -> ARANDELAS DE COBRE17 x 20 x 1,5 | B1337: ARANDELAS DE COBRE | C1337: 17 x 20 x 1,5 | D1337: INYECTORES - BERLINGO D | E1337: =+VLOOKUP(Table_2[[#This Row],[ID]],LISTAS[],3,0) -> 1775.1 | F1337: 009.009.0013
A1338: =+Table_2[[#This Row],[Producto]]&Table_2[[#This Row],[Numero]] -> ARANDELAS DE COBRE6x10 | B1338: ARANDELAS DE COBRE | C1338: 6x10 | D1338: 6x10 | E1338: =+VLOOKUP(Table_2[[#This Row],[ID]],LISTAS[],3,0) -> 402.79 | F1338: 009.009.0014
... A1704: =+Table_2[[#This Row],[Producto]]&Table_2[[#This Row],[Numero]] -> SUPLEMENTO 0,861x73 | B1704: SUPLEMENTO 0,8 | C1704: 61x73 | D1704: 61x73 | E1704: =+VLOOKUP(Table_2[[#This Row],[ID]],LISTAS[],3,0) -> 3294.58 | F1704: 056.056.0108
A1705: =+Table_2[[#This Row],[Producto]]&Table_2[[#This Row],[Numero]] -> RACORD - ACOPLES - REDUCCIONES - ENTREROSCAS1 | B1705: RACORD - ACOPLES - REDUCCIONES - ENTREROSCAS | C1705: 1 | D1705: PTA ACOPLE RAP 1/4 R M 1/4 BSPT | E1705: =+VLOOKUP(Table_2[[#This Row],[ID]],LISTAS[],3,0) -> 2866.48 | F1705: 042.042.0003
A1706: =+Table_2[[#This Row],[Producto]]&Table_2[[#This Row],[Numero]] -> RACORD - ACOPLES - REDUCCIONES - ENTREROSCAS2 | B1706: RACORD - ACOPLES - REDUCCIONES - ENTREROSCAS | C1706: 2 | D1706: PTA ACOPLE RAP 1/4 MANG 6 MM | E1706: =+VLOOKUP(Table_2[[#This Row],[ID]],LISTAS[],3,0) -> 3676.01 | F1706: 042.042.0004
A1707: =+Table_2[[#This Row],[Producto]]&Table_2[[#This Row],[Numero]] -> RACORD - ACOPLES - REDUCCIONES - ENTREROSCAS3 | B1707: RACORD - ACOPLES - REDUCCIONES - ENTREROSCAS | C1707: 3 | D1707: PTA ACOPLE RAP 1/4 MANG 8 MM | E1707: =+VLOOKUP(Table_2[[#This Row],[ID]],LISTAS[],3,0) -> 3676.01 | F1707: 042.042.0005
A1708: =+Table_2[[#This Row],[Producto]]&Table_2[[#This Row],[Numero]] -> RACORD - ACOPLES - REDUCCIONES - ENTREROSCAS4 | B1708: RACORD - ACOPLES - REDUCCIONES - ENTREROSCAS | C1708: 4 | D1708: PTA ACOPLE RAP 1/4 MANG 9,5 MM | E1708: =+VLOOKUP(Table_2[[#This Row],[ID]],LISTAS[],3,0) -> 5437.86 | F1708: 042.042.0006
A1709: =+Table_2[[#This Row],[Producto]]&Table_2[[#This Row],[Numero]] -> RACORD - ACOPLES - REDUCCIONES - ENTREROSCAS5 | B1709: RACORD - ACOPLES - REDUCCIONES - ENTREROSCAS | C1709: 5 | D1709: PTA ACOPLE RAP 1/4 MANG 12,7 MM | E1709: =+VLOOKUP(Table_2[[#This Row],[ID]],LISTAS[],3,0) -> 5979.59 | F1709: 042.042.0007
A1710: =+Table_2[[#This Row],[Producto]]&Table_2[[#This Row],[Numero]] -> RACORD - ACOPLES - REDUCCIONES - ENTREROSCAS6 | B1710: RACORD - ACOPLES - REDUCCIONES - ENTREROSCAS | C1710: 6 | D1710: RACORD R M 1/8 BSPT MANG 6 MM | E1710: =+VLOOKUP(Table_2[[#This Row],[ID]],LISTAS[],3,0) -> 2013.84 | F1710: 042.042.0008
...

Sheet LISTAS
A1: ID | B1: Codigo BS GESTION | C1: Precio
A2: PLASTICOS1 | B2: 039.039.0003 | C2: 1159.02
A3: PLASTICOS2 | B3: 039.039.0004 | C3: 578.93
A4: PLASTICOS3 | B4: 039.039.0005 | C4: 629.53
A5: PLASTICOS4 | B5: 039.039.0006 | C5: 654.85
A6: PLASTICOS5 | B6: 039.039.0007 | C6: 727.61
A7: PLASTICOS6 | B7: 039.039.0008 | C7: 914.71
A8: PLASTICOS7 | B8: 039.039.0009 | C8: 578.93
A9: PLASTICOS8 | B9: 039.039.0010 | C9: 654.85
A10: PLASTICOS9 | B10: 039.039.0011 | C10: 680.9
A11: PLASTICOS10 | B11: 039.039.0012 | C11: 771.26
A12: PLASTICOS11 | B12: 039.039.0013 | C12: 917.77
A13: PLASTICOS12 | B13: 039.039.0014 | C13: 933.24
... A2079: CARBONES109 - 13,7 x 7 x 6 | B2079: 020.020.0042 | C2079: 5979.93
A2080: CARBONESExhibidor | C2080: 0
A2081: KIT RIFLE5/2 máster Potenciado + Pistón + Arandela | B2081: 033.033.0003 | C2081: 0
A2082: KIT RIFLEMáster Potenciado Coop + Pistón + Arandela | B2082: 033.033.0004 | C2082: 0
A2083: KIT RIFLEJunior + Pistón + Arandela | B2083: 033.033.0005 | C2083: 0
A2084: ESPINAS ELASTICAS2 x 12 | B2084: 028.028.0003 | C2084: 52.79
A2085: ESPINAS ELASTICAS2 x 16 | B2085: 028.028.0004 | C2085: 70.39
A2086: ESPINAS ELASTICAS2 x 20 | B2086: 028.028.0005 | C2086: 87.97
A2087: ESPINAS ELASTICAS2,5 x 14 | B2087: 028.028.0006 | C2087: 77.18
A2088: ESPINAS ELASTICAS2,5 x 16 | B2088: 028.028.0007 | C2088: 88.17
A2089: ESPINAS ELASTICAS2,5 x 26 | B2089: 028.028.0008 | C2089: 143.31
A2090: ESPINAS ELASTICAS2,5 x 30 | B2090: 028.028.0009 | C2090: 165.43
A2091: ESPINAS ELASTICAS3 x 14 | B2091: 028.028.0010 | C2091: 94.37
A2092: ESPINAS ELASTICAS3 x 16 | B2092: 028.028.0011 | C2092: 121.36
... A2436: CONECTORES NEUMÁTICOS228 | B2436: 023.023.0069 | C2436: 1212.48
A2437: CONECTORES NEUMÁTICOS229 | B2437: 023.023.0070 | C2437: 2556.43 | I2437: 063.063.0028
A2438: CONECTORES NEUMÁTICOS230 | B2438: 023.023.0071 | C2438: 2850.1 | I2438: 063.063.0029
A2439: CONECTORES NEUMÁTICOS231 | B2439: 023.023.0072 | C2439: 3953.83 | I2439: 063.063.0030
A2440: CONECTORES NEUMÁTICOS49 | B2440: 023.023.0073 | C2440: 0 | I2440: 063.063.0031
A2441: CONECTORES NEUMÁTICOS51 | B2441: 023.023.0074 | C2441: 0 | I2441: 063.063.0032
A2442: CONECTORES NUEVA INCORPORACION3 | B2442: 024.024.0003 | C2442: 3239.17 | I2442: 017.017.0003
A2443: CONECTORES NUEVA INCORPORACION7 | B2443: 024.024.0004 | C2443: 4356.83 | I2443: 017.017.0004
A2444: CONECTORES NUEVA INCORPORACION96 | B2444: 024.024.0005 | C2444: 1224.17 | I2444: 017.017.0005
A2445: CONECTORES NUEVA INCORPORACION107 | B2445: 024.024.0006 | C2445: 3154.29 | I2445: 017.017.0006
A2446: CONECTORES NUEVA INCORPORACION139 | B2446: 024.024.0007 | C2446: 1283.17 | I2446: 017.017.0007
A2447: CONECTORES NUEVA INCORPORACION152 | B2447: 024.024.0008 | C2447: 3540.97 | I2447: 017.017.0008
A2448: CONECTORES NUEVA INCORPORACION156 | B2448: 024.024.0009 | C2448: 3925.98 | I2448: 017.017.0009
... A2454: CONECTORES NUEVA INCORPORACION166 | B2454: 024.024.0015 | C2454: 6122.18 | I2454: 017.017.0015
A2455: CONECTORES NUEVA INCORPORACION167 | B2455: 024.024.0016 | C2455: 7988.06
A2456: CONECTORES NUEVA INCORPORACION240 | B2456: 024.024.0017 | C2456: 4316.42
A2457: CONECTORES NUEVA INCORPORACION241 | B2457: 024.024.0018 | C2457: 4929.58
A2458: CONECTORES NUEVA INCORPORACION242 | B2458: 024.024.0019 | C2458: 4911.48
A2459: CONECTORES NUEVA INCORPORACION243 | B2459: 024.024.0020 | C2459: 9372.93
A2460: CONECTORES NUEVA INCORPORACION248 | B2460: 024.024.0021 | C2460: 16076.31
A2461: CONECTORES NUEVA INCORPORACION249 | B2461: 024.024.0022 | C2461: 18755.54
A2462: CONECTORES NUEVA INCORPORACION251 | B2462: 024.024.0023 | C2462: 21612.8
A2463: CONECTORES NUEVA INCORPORACION256 | B2463: 024.024.0024 | C2463: 16793.29
A2464: CONECTORES NUEVA INCORPORACION257 | B2464: 024.024.0025 | C2464: 21969.83
A2465: CONECTORES NUEVA INCORPORACION263 | B2465: 024.024.0026 | C2465: 15539.31
A2466: CONECTORES NUEVA INCORPORACION264 | B2466: 024.024.0027 | C2466: 19644.74
... A2780: ABRAZADERAS C/ GOMA - ALUMINIO35 | B2780: 002.002.0020 | C2780: 2150.4
A2781: ARANDELAS DE GOMA LINEA PESADAGaveta | C2781: 0
A2782: CONECTORES NUEVA INCORPORACIONGaveta | C2782: 0
A2783: ABRAZADERAS C/ GOMA - AC INOXIDABLEGaveta | C2783: 0
A2784: ABRAZADERAS C/ GOMA - ALUMINIOGaveta | C2784: 0
A2785: RESORTES LINEA BULONERAGaveta | C2785: 0
A2786: BORNES PARA BATERIAGaveta | C2786: 0
A2787: ABRAZADERAS GRAMPAS UGaveta | C2787: 0
A2788: TAPONES DE CARTERGaveta | C2788: 0
A2789: ARANDELAS DE ALUMINIOGaveta | C2789: 0
A2790: ARANDELAS DE COBREGaveta | C2790: 0
A2791: ARANDELAS DE POLIPROPILENOGaveta | C2791: 0
A2792: REGATONESGaveta | C2792: 0
... A2825: GANCHOS - CHAVETASGaveta | C2825: 0
A2826: VariosVarios Ch | B2826: 065.065.0004 | C2826: 16800
A2827: VariosVarios Gr | B2827: 066.066.0004 | C2827: 30000
A2828: Gavetach | B2828: 076.576.0002 | C2828: 17500
A2829: Gavetame | B2829: 077.577.0002 | C2829: 18000
A2830: Gavetagr | B2830: 078.578.0002 | C2830: 24000
A2831: Gavetas1 - 30x49x10 - Esp. 20 | B2831: 030.030.0003 | C2831: 24000
A2832: Gavetas2 - 25x42x8 - Esp. 20 | B2832: 030.030.0004 | C2832: 18000
A2833: Gavetas3 - 25x42x8 - Esp. 24 | B2833: 030.030.0005 | C2833: 18000
A2834: Gavetas4 - 25x42x7 - Esp. 30 | B2834: 030.030.0006 | C2834: 18000
A2835: Gavetas5 - 25x42x7 - Esp. 35 | B2835: 030.030.0007 | C2835: 18000
A2836: Gavetas6 - 25x42x5 - Esp. 35 | B2836: 030.030.0008 | C2836: 17500
A2837: Gavetas7 - 25x49x7 - Esp. 40 | B2837: 030.030.0009 | C2837: 18000
... A3603: CLIPS IMPORTADOS969 | B3603: 097.597.0302 | C3603: 913.04
A3604: CLIPS IMPORTADOS970 | B3604: 097.597.0303 | C3604: 913.04 | F3604: TORNILLERIA ESPECIAL1 | G3604: =IFERROR(VLOOKUP(F3604,$A$3622:$B$3771,2,0),"") -> 096.596.0002 | H3604: 843
A3605: CLIPS IMPORTADOS971 | B3605: 097.597.0304 | C3605: 1000 | F3605: TORNILLERIA ESPECIAL3 | G3605: =IFERROR(VLOOKUP(F3605,$A$3622:$B$3771,2,0),"") -> 096.596.0003 | H3605: 890
A3606: CLIPS IMPORTADOS972 | B3606: 097.597.0305 | C3606: 1130.43 | F3606: TORNILLERIA ESPECIAL4 | G3606: =IFERROR(VLOOKUP(F3606,$A$3622:$B$3771,2,0),"") -> 096.596.0004 | H3606: 843
A3607: CLIPS IMPORTADOS973 | B3607: 097.597.0306 | C3607: 1000 | F3607: TORNILLERIA ESPECIAL5 | G3607: =IFERROR(VLOOKUP(F3607,$A$3622:$B$3771,2,0),"") -> 096.596.0005 | H3607: 843
A3608: CLIPS IMPORTADOS974 | B3608: 097.597.0307 | C3608: 1065.22 | F3608: TORNILLERIA ESPECIAL6 | G3608: =IFERROR(VLOOKUP(F3608,$A$3622:$B$3771,2,0),"") -> 096.596.0006 | H3608: 995
A3609: CLIPS IMPORTADOS975 | B3609: 097.597.0308 | C3609: 1130.43 | F3609: TORNILLERIA ESPECIAL7 | G3609: =IFERROR(VLOOKUP(F3609,$A$3622:$B$3771,2,0),"") -> 096.596.0007 | H3609: 890
A3610: CLIPS IMPORTADOS976 | B3610: 097.597.0309 | C3610: 1217.39 | F3610: TORNILLERIA ESPECIAL9 | G3610: =IFERROR(VLOOKUP(F3610,$A$3622:$B$3771,2,0),"") -> 096.596.0008 | H3610: 890
A3611: CLIPS IMPORTADOS977 | B3611: 097.597.0310 | C3611: 913.04 | F3611: TORNILLERIA ESPECIAL13 | G3611: =IFERROR(VLOOKUP(F3611,$A$3622:$B$3771,2,0),"") -> 096.596.0009 | H3611: 990
A3612: CLIPS IMPORTADOS978 | B3612: 097.597.0311 | C3612: 1130.43 | F3612: TORNILLERIA ESPECIAL14 | G3612: =IFERROR(VLOOKUP(F3612,$A$3622:$B$3771,2,0),"") -> 096.596.0068 | H3612: 1874.3
A3613: CLIPS IMPORTADOS979 | B3613: 097.597.0312 | C3613: 1130.43 | F3613: TORNILLERIA ESPECIAL16 | G3613: =IFERROR(VLOOKUP(F3613,$A$3622:$B$3771,2,0),"") -> 096.596.0010 | H3613: 843
A3614: CLIPS IMPORTADOS980 | B3614: 097.597.0313 | C3614: 1000 | F3614: TORNILLERIA ESPECIAL17 | G3614: =IFERROR(VLOOKUP(F3614,$A$3622:$B$3771,2,0),"") -> 096.596.0011 | H3614: 843
A3615: CLIPS IMPORTADOS981 | B3615: 097.597.0314 | C3615: 1456.52 | F3615: TORNILLERIA ESPECIAL18 | G3615: =IFERROR(VLOOKUP(F3615,$A$3622:$B$3771,2,0),"") -> 096.596.0012 | H3615: 843
... A3681: TORNILLERIA ESPECIAL168 | B3681: 096.596.0058 | C3681: 995 | F3681: TORNILLERIA ESPECIAL210 | G3681: =IFERROR(VLOOKUP(F3681,$A$3622:$B$3771,2,0),"") -> 096.596.0079 | H3681: 1860
A3682: TORNILLERIA ESPECIAL172 | B3682: 096.596.0059 | C3682: 1115
A3683: TORNILLERIA ESPECIAL173 | B3683: 096.596.0060 | C3683: 1115
A3684: TORNILLERIA ESPECIAL182 | B3684: 096.596.0061 | C3684: 1290
A3685: TORNILLERIA ESPECIAL183 | B3685: 096.596.0062 | C3685: 1290
A3686: TORNILLERIA ESPECIAL184 | B3686: 096.596.0063 | C3686: 1390
A3687: TORNILLERIA ESPECIAL200 | B3687: 096.596.0064 | C3687: 890
A3688: TORNILLERIA ESPECIAL202 | B3688: 096.596.0065 | C3688: 1090
...

Sheet Imagen
A1: ID | B1: IMAGEN
A2: PLASTICOS1 | B2: http://http2.mlstatic.com/D_708492-MLA72045130481_102023-F.jpg
A3: PLASTICOS2 | B3: http://http2.mlstatic.com/D_785905-MLA71988387406_102023-F.jpg
A4: PLASTICOS3 | B4: http://http2.mlstatic.com/D_878027-MLA72239756252_102023-F.jpg
A5: PLASTICOS4 | B5: http://http2.mlstatic.com/D_741302-MLA71988387408_102023-F.jpg
A6: PLASTICOS5 | B6: http://http2.mlstatic.com/D_986792-MLA72240891774_102023-F.jpg
A7: PLASTICOS6 | B7: http://http2.mlstatic.com/D_953256-MLA71988435968_102023-F.jpg
A8: PLASTICOS7 | B8: http://http2.mlstatic.com/D_778884-MLA71988387412_102023-F.jpg
A9: PLASTICOS8 | B9: http://http2.mlstatic.com/D_881846-MLA71988387472_102023-F.jpg
A10: PLASTICOS9 | B10: http://http2.mlstatic.com/D_647342-MLA72293218763_102023-F.jpg
A11: PLASTICOS10 | B11: http://http2.mlstatic.com/D_724144-MLA72292952705_102023-F.jpg
A12: PLASTICOS11 | B12: http://http2.mlstatic.com/D_790405-MLA72292952961_102023-F.jpg
... A14: PLASTICOS13 | B14: http://http2.mlstatic.com/D_868791-MLA71988436048_102023-F.jpg
A15: PLASTICOS14
A16: PLASTICOS15 | B16: http://http2.mlstatic.com/D_849599-MLA72045130573_102023-F.jpg
A17: PLASTICOS16 | B17: http://http2.mlstatic.com/D_759357-MLA71988436056_102023-F.jpg
A18: PLASTICOS17 | B18: http://http2.mlstatic.com/D_784053-MLA71988436060_102023-F.jpg
A19: PLASTICOS18 | B19: http://http2.mlstatic.com/D_767299-MLA71988387492_102023-F.jpg
A20: PLASTICOS19 | B20: http://http2.mlstatic.com/D_633062-MLA72045130585_102023-F.jpg
A21: PLASTICOS20 | B21: http://http2.mlstatic.com/D_651074-MLA71988387494_102023-F.jpg
A22: PLASTICOS21 | B22: http://http2.mlstatic.com/D_915039-MLA72045130587_102023-F.jpg
A23: PLASTICOS22 | B23: http://http2.mlstatic.com/D_808914-MLA71988436066_102023-F.jpg
A24: PLASTICOS23 | B24: http://http2.mlstatic.com/D_795009-MLA72045130593_102023-F.jpg
A25: PLASTICOS24 | B25: http://http2.mlstatic.com/D_839604-MLA72304258543_102023-F.jpg
A26: PLASTICOS25 | B26: http://http2.mlstatic.com/D_982789-MLA71988387498_102023-F.jpg
A27: PLASTICOS26 | B27: http://http2.mlstatic.com/D_939078-MLA72045130601_102023-F.jpg
... A49: PLASTICOS48 | B49: http://http2.mlstatic.com/D_910527-MLA71988436122_102023-F.jpg
A50: PLASTICOS49
A51: PLASTICOS50 | B51: http://http2.mlstatic.com/D_874828-MLA71988436130_102023-F.jpg
A52: PLASTICOS51 | B52: http://http2.mlstatic.com/D_949801-MLA72045130647_102023-F.jpg
A53: PLASTICOS52 | B53: http://http2.mlstatic.com/D_704935-MLA72045130649_102023-F.jpg
A54: PLASTICOS53 | B54: http://http2.mlstatic.com/D_618901-MLA72292972649_102023-F.jpg
A55: PLASTICOS54 | B55: http://http2.mlstatic.com/D_723830-MLA71988436146_102023-F.jpg
A56: PLASTICOS55 | B56: http://http2.mlstatic.com/D_915339-MLA71988436142_102023-F.jpg
A57: PLASTICOS56 | B57: http://http2.mlstatic.com/D_681688-MLA72292952709_102023-F.jpg
A58: PLASTICOS57
A59: PLASTICOS58 | B59: http://http2.mlstatic.com/D_630670-MLA71988387564_102023-F.jpg
A60: PLASTICOS59 | B60: http://http2.mlstatic.com/D_614810-MLA72409121524_102023-F.jpg
A61: PLASTICOS60 | B61: http://http2.mlstatic.com/D_859108-MLA71988387576_102023-F.jpg
A62: PLASTICOS61 | B62: http://http2.mlstatic.com/D_702377-MLA71988387574_102023-F.jpg
A63: PLASTICOS62 | B63: http://http2.mlstatic.com/D_890606-MLA71988436162_102023-F.jpg
A64: PLASTICOS63 | B64: http://http2.mlstatic.com/D_836705-MLA72292972697_102023-F.jpg
A65: PLASTICOS64 | B65: http://http2.mlstatic.com/D_711277-MLA71988436164_102023-F.jpg
A66: PLASTICOS65 | B66: http://http2.mlstatic.com/D_988660-MLA72045130659_102023-F.jpg
A67: PLASTICOS66 | B67: http://http2.mlstatic.com/D_921941-MLA71988436168_102023-F.jpg
A68: PLASTICOS67 | B68: http://http2.mlstatic.com/D_769469-MLA72045130665_102023-F.jpg
A69: PLASTICOS69 | B69: http://http2.mlstatic.com/D_922989-MLA72045130667_102023-F.jpg
A70: PLASTICOS70 | B70: http://http2.mlstatic.com/D_859666-MLA71988387592_102023-F.jpg
... A98: PLASTICOS100 | B98: http://http2.mlstatic.com/D_977135-MLA71988436234_102023-F.jpg
A99: PLASTICOS101
A100: PLASTICOS102 | B100: http://http2.mlstatic.com/D_699750-MLA71988436232_102023-F.jpg
A101: PLASTICOS103 | B101: http://http2.mlstatic.com/D_919006-MLA71988436238_102023-F.jpg
A102: PLASTICOS104 | B102: http://http2.mlstatic.com/D_960675-MLA72045130725_102023-F.jpg
A103: PLASTICOS105 | B103: http://http2.mlstatic.com/D_978684-MLA71988436240_102023-F.jpg
A104: PLASTICOS106 | B104: http://http2.mlstatic.com/D_714361-MLA72045130729_102023-F.jpg
A105: PLASTICOS107 | B105: http://http2.mlstatic.com/D_955327-MLA72292972833_102023-F.jpg
A106: PLASTICOS108 | B106: http://http2.mlstatic.com/D_884455-MLA72293219047_102023-F.jpg
A107: PLASTICOS109 | B107: http://http2.mlstatic.com/D_757564-MLA72045130737_102023-F.jpg
A108: PLASTICOS110 | B108: http://http2.mlstatic.com/D_870556-MLA72292952729_102023-F.jpg
A109: PLASTICOS111 | B109: http://http2.mlstatic.com/D_638439-MLA71988387652_102023-F.jpg
A110: PLASTICOS112 | B110: http://http2.mlstatic.com/D_796169-MLA71988436254_102023-F.jpg
A111: PLASTICOS113 | B111: http://http2.mlstatic.com/D_903071-MLA72045130741_102023-F.jpg
... A123: PLASTICOS125 | B123: http://http2.mlstatic.com/D_896297-MLA71988387678_102023-F.jpg
A124: PLASTICOS126
A125: PLASTICOS127 | B125: http://http2.mlstatic.com/D_742896-MLA71988436284_102023-F.jpg
A126: PLASTICOS128
A127: PLASTICOS129
A128: PLASTICOS130
A129: PLASTICOS131 | B129: http://http2.mlstatic.com/D_868530-MLA71988387414_102023-F.jpg
A130: PLASTICOS132 | B130: http://http2.mlstatic.com/D_846247-MLA72098808088_102023-F.jpg
A131: PLASTICOS133 | B131: http://http2.mlstatic.com/D_629655-MLA72239320568_102023-F.jpg
A132: PLASTICOS134
A133: PLASTICOS135
A134: PLASTICOS136 | B134: http://http2.mlstatic.com/D_709826-MLA72045130769_102023-F.jpg
A135: PLASTICOS137
A136: PLASTICOS138 | B136: http://http2.mlstatic.com/D_854084-MLA72292972873_102023-F.jpg
A137: PLASTICOS139 | B137: http://http2.mlstatic.com/D_915672-MLA71988387690_102023-F.jpg
A138: PLASTICOS140 | B138: http://http2.mlstatic.com/D_955509-MLA72045130771_102023-F.jpg
A139: PLASTICOS141 | B139: http://http2.mlstatic.com/D_857643-MLA72293218839_102023-F.jpg
A140: PLASTICOS142 | B140: http://http2.mlstatic.com/D_779434-MLA71988387694_102023-F.jpg
A141: PLASTICOS143 | B141: http://http2.mlstatic.com/D_646310-MLA72045130777_102023-F.jpg
A142: PLASTICOS144 | B142: http://http2.mlstatic.com/D_616556-MLA71988387698_102023-F.jpg
A143: PLASTICOS145 | B143: http://http2.mlstatic.com/D_695773-MLA71988387702_102023-F.jpg
A144: PLASTICOS146
A145: PLASTICOS147 | B145: http://http2.mlstatic.com/D_898294-MLA72045130785_102023-F.jpg
A146: PLASTICOS148 | B146: http://http2.mlstatic.com/D_853418-MLA72045130789_102023-F.jpg
A147: PLASTICOS149 | B147: http://http2.mlstatic.com/D_845029-MLA71988387706_102023-F.jpg
A148: PLASTICOS150 | B148: http://http2.mlstatic.com/D_723314-MLA72292953009_102023-F.jpg
A149: PLASTICOS151 | B149: http://http2.mlstatic.com/D_695993-MLA72292972461_102023-F.jpg
A150: PLASTICOS152 | B150: http://http2.mlstatic.com/D_651701-MLA72045130799_102023-F.jpg
A151: PLASTICOS153 | B151: http://http2.mlstatic.com/D_759077-MLA71988436310_102023-F.jpg
A152: PLASTICOS154 | B152: http://http2.mlstatic.com/D_634519-MLA72292953117_102023-F.jpg
A153: PLASTICOS155 | B153: http://http2.mlstatic.com/D_810033-MLA71988436312_102023-F.jpg
A154: PLASTICOS156 | B154: http://http2.mlstatic.com/D_690049-MLA72292952907_102023-F.jpg
A155: PLASTICOS157 | B155: http://http2.mlstatic.com/D_952314-MLA72293219189_102023-F.jpg
A156: PLASTICOS158 | B156: http://http2.mlstatic.com/D_831161-MLA72045130807_102023-F.jpg
A157: PLASTICOS159
A158: PLASTICOS160 | B158: http://http2.mlstatic.com/D_697507-MLA71988436322_102023-F.jpg
A159: PLASTICOS161 | B159: http://http2.mlstatic.com/D_976147-MLA72045130817_102023-F.jpg
A160: PLASTICOS162 | B160: http://http2.mlstatic.com/D_833829-MLA71988387732_102023-F.jpg
...
